[1,["12Y9dMgWdJKJGmTiZyQR9H@fc873","a0X46kalxI7rAIyoAO2Dbm","a3zQCfCrBCDZJ4uf2rk5u8","fa6F+k8/FC2I1GkbYCywIv@8574e","08HYwIVAZNeYPBbYphmz5/","d6pGaXRkhDs7/Schq0UWX1","f3sS5Mm11KH5+K90e0GEV8","80H+3Ccu1NdKFwZpL1EBKo","a7vs48HolPFaLEDIP4INe+","3eL1/EKRxD1aNu0jKfZ2HA","f6SJZOjTJB/JrJeh5xTdF7","17AdJtm/9BPbORXOdkC5GQ@6c48a","8cQG1cHypLhqhoHNXLRZVg@6c48a","e4F73apRRIH6Hk+JcFsqhC@6c48a","12fR903FhEubbVuSKGPP3a@6c48a","9939dg0u1K/4uRV+EoOQvl@6c48a","c0NqL9L9NDyJtQ0D0z0p+Z@6c48a","8cxjX9tBdNJJfwSrJc4nsi@6c48a","31BSzPpQBM0a//U6akm4sk","fcjHRwXaNCnI3RXn7IoLkm","6039Nj/ehLtKgQaRNL+kTI","97NtWKdVRKEL1T3kHKbTlM","6aBnh8hl5KWrj751BEj2+N","62k4cKBE1NUqoodkFo5Uqf","20adllLylO2Y3rGHOkpUUw","dbWGoXhVlPqpE8L2c3H3HE","82CQw8DsJOYpMnKmfgYfQ2","4a60jjUwRBtJENMjm6DmS1","b3m1gpu91C6Yhmr9JeEdBG","74Ejm6roZL+JhjWKF48X04","de0eMZtWVJA7wPyNG+LZPa","cbxZHDj/BCO5PoXr28IyTA","3b+gDSy8xCsKhdJ9Ca44lK","109PWqP9VP0aOGCj6TVNuO","aaVpTNDyhIdZQD5Ui8IeEq","b5tBRGKH1Otr9Dqocbnop3","d34s3Q9npLK7mC5Mqv0Plp","08FvSebs5GnZnCaYXbFbKw","12LmwqxzNG1q6uxfNGflCQ","b2TneFk+JFbqInk/HMxJ9w","35oC7M5ehGYYI/tTqU8/3J","08VUMX305LhoqJP9M8WPWg","efbEcFwDpO2Yi8ZE9Igz21","5aaWd3KeFN3IfKHeN4fdLC","b1oE83vc1IlbtNVy0Vugih","060KdXWABBAo9hp8wdVZCc","cbyqs5y4VHrY7VNmONNYaN","35OFUVgapMEryaGhum/+1R","f5+Mqi2w5B7IHAELvKnJVJ","b5YqcuRV1JpaNYcfYlxXRN","6dTsa+EfZEDrSgv8tRcXUg","a6RIhHthxFfbhok+rkhVLb","9f/DxKGU5Ox5pxW7C2PWRX","00PiHF6WhLbZIXzcMqd15K","eazdzKpr1L+oSpnkfTH7dk","d9lBDklp5FxZjaRKKESRq0","aburvfh1ZNYo6rjYYsb50B","fe4IFHBypII5nUTJX9yySn","95SF9ClThB17/lM2oMLQo1","69S5aE5UNHcrY7/BBtq4oA","b8LKOxzyROYaVlOdQuVKZ2@ccc7e","fcRFJ9XvVOnqUstfr/FIuv@59ded","aeK6asclFLE6oT8vc021Sh@6c48a","b8sY86LN5PwKhOfnbb5sBt@d7076","faxx6g20ZKbIU2yERv9PmC@922c6","8ftJ2AP7BD9LdbESEfub03","0eFNyEWhhHuq3PWseBjU+n","b9SSJs2CpG9r/nyCJvNBB/","56H1/ouuFCqIXPLSbXXXAm@6c48a","faxx6g20ZKbIU2yERv9PmC@e292e","faxx6g20ZKbIU2yERv9PmC@4e825","faxx6g20ZKbIU2yERv9PmC@f9c4e","faxx6g20ZKbIU2yERv9PmC@c869e","faxx6g20ZKbIU2yERv9PmC@438fe","faxx6g20ZKbIU2yERv9PmC@14d99","43vC/Knm5P8p7iybqZrYTh@0624b","75GRWC8fBPdLOCr+fqOWTY","9by5t2PndLM4pKQu4JUMUq","61FDv6OhtPqK8srLiQWFtJ"],["root","asset","node","value","_parent","_mesh","mainTexture","_effectAsset","targetInfo","data","target","source","_graph","_skeleton"],[["cc.Node",["_name","_objFlags","__editorExtras__","_prefab","_parent","_children","_lpos","_components","_lrot","_euler","_lscale"],0,4,1,2,5,9,5,5,5],["cc.PrefabInstance",["fileId","prefabRootNode","propertyOverrides","removedComponents","mountedComponents"],2,1,9,9,9],["cc.Material",["_name","_states","_defines","_techIdx","_props"],-1,12],["cc.Node",["_name","_parent","_children","_prefab","_lpos","_lrot","_euler"],2,1,9,4,5,5,5],["cc.RigidBody",["_group","_useGravity","_type","node","__prefab"],0,1,4],["cc.ModelBakeSettings",["_castShadow","_receiveShadow"],1],["cc.Prefab",["_name"],2],["cc.UITransform",["node","__prefab"],3,1,4],["cc.CompPrefabInfo",["fileId"],2],["cc.PrefabInfo",["fileId","instance","root","asset","targetOverrides","nestedPrefabInstanceRoots"],1,1,1,9,2],["cc.PrefabInfo",["fileId","instance","targetOverrides","nestedPrefabInstanceRoots","root","asset"],-1,1,1],["cc.PrefabInfo",["fileId","targetOverrides","nestedPrefabInstanceRoots","root","instance","asset"],0,1,4,6],["cc.PrefabInfo",["fileId","instance","targetOverrides","root","asset","nestedPrefabInstanceRoots"],0,1,1,2],["cc.TargetOverrideInfo",["source","sourceInfo","target","targetInfo"],3,1,4,1,4],["cc.TargetInfo",["localID"],2],["CCPropertyOverrideInfo",["value","propertyPath","targetInfo"],1,1],["CCPropertyOverrideInfo",["propertyPath","targetInfo","value"],2,1,8],["CCPropertyOverrideInfo",["propertyPath","targetInfo","value"],2,4,8],["CCPropertyOverrideInfo",["propertyPath","targetInfo","value"],2,4,6],["CCPropertyOverrideInfo",["propertyPath","targetInfo","value"],2,1,6],["CCPropertyOverrideInfo",["propertyPath","targetInfo","value"],2,1,1],["CCPropertyOverrideInfo",["value","propertyPath","targetInfo"],1,4],["CCPropertyOverrideInfo",["propertyPath","targetInfo","value"],2,4,1],["cc.SphereCollider",["_isTrigger","_radius","node","__prefab"],1,1,4],["cc.MeshRenderer",["_name","node","__prefab","_materials","bakeSettings","_mesh"],2,1,4,3,4,6],["cc.MountedComponentsInfo",["targetInfo","components"],3,4,9],["cc.animation.AnimationController",["node","__prefab","_graph"],3,1,4,6],["cc.Skeleton",["_name","_hash","_joints","_bindposes"],0,12],["cc.SkeletalAnimation",["node","__prefab"],3,1,4],["cc.SkinnedMeshRenderer",["_shadowCastingMode","node","__prefab","_materials","bakeSettings","_skinningRoot","_mesh","_skeleton"],2,1,4,3,4,1,6,6],["cc.Mesh",["_native","_hash","_struct"],1,11]],[[16,0,1,2,2],[10,0,1,2,3,4,5,5],[14,0,2],[15,0,1,2,3],[11,0,1,2,3,4,5,4],[0,1,2,4,3,3],[1,0,1,2,2],[0,0,4,5,3,6,8,9,2],[8,0,2],[18,0,1,2,2],[17,0,1,2,2],[0,0,4,3,6,2],[3,0,1,2,3,4,5,6,2],[7,0,1,1],[24,0,1,2,3,4,5,2],[5,1],[0,0,4,7,3,8,10,9,2],[2,0,1,2,4,4],[0,0,4,5,7,3,2],[6,0,2],[0,0,4,5,3,2],[0,0,4,5,3,6,2],[0,0,5,3,6,2],[12,0,1,2,3,4,5,4],[0,0,4,7,3,6,2],[23,0,1,2,3,3],[0,0,5,7,3,2],[0,0,4,5,7,3,6,2],[0,1,2,3,3],[0,0,4,5,3,10,2],[0,0,5,3,6,8,9,2],[13,0,1,2,3,1],[1,0,1,4,2,3,2],[19,0,1,2,2],[21,0,1,2,3],[22,0,1,2,2],[4,0,1,3,4,3],[25,0,1,1],[26,0,1,2,1],[2,0,3,1,2,4,5],[0,0,4,7,3,6,8,10,9,2],[0,0,4,7,3,2],[3,0,1,2,3,4,2],[9,0,1,2,3,4,5,3],[1,0,1,2,3,2],[20,0,1,2,2],[4,0,2,3,4,3],[5,0,1,3],[27,0,1,2,3,4],[28,0,1,1],[29,0,1,2,3,4,5,6,7,2],[30,0,1,2,3]],[[[[17,"Body",[{"rasterizerState":{},"depthStencilState":{},"blendState":{"targets":[{}]}},{"rasterizerState":{},"depthStencilState":{},"blendState":{"targets":[{}]}},{"rasterizerState":{},"depthStencilState":{},"blendState":{"targets":[{}]}}],[{"USE_TEXTURE":true},{},{}],[[[{},"mainTexture",6,0],{},{}],11,0,0]]],0,0,[0,0],[6,7],[11,2]],[[[39,"material",1,[{"rasterizerState":{},"depthStencilState":{},"blendState":{"targets":[{}]}},{"rasterizerState":{},"depthStencilState":{},"blendState":{"targets":[{}]}},{"rasterizerState":{},"depthStencilState":{},"blendState":{"targets":[{}]}}],[{"USE_TEXTURE":true},{},{}],[[[{},"mainTexture",6,0],{},{}],11,0,0]]],0,0,[0,0],[6,7],[12,2]],[[[17,"Egg 17C",[{"rasterizerState":{},"depthStencilState":{},"blendState":{"targets":[{}]}},{"rasterizerState":{},"depthStencilState":{},"blendState":{"targets":[{}]}},{"rasterizerState":{},"depthStencilState":{},"blendState":{"targets":[{}]}}],[{"USE_TEXTURE":true},{},{}],[[[{},"mainTexture",6,0],{},{}],11,0,0]]],0,0,[0,0],[6,7],[13,2]],[[[17,"Egg 17A",[{"rasterizerState":{},"depthStencilState":{},"blendState":{"targets":[{}]}},{"rasterizerState":{},"depthStencilState":{},"blendState":{"targets":[{}]}},{"rasterizerState":{},"depthStencilState":{},"blendState":{"targets":[{}]}}],[{"USE_TEXTURE":true},{},{}],[[[{},"mainTexture",6,0],{},{}],11,0,0]]],0,0,[0,0],[6,7],[14,2]],[[[17,"Bear05",[{"rasterizerState":{},"depthStencilState":{},"blendState":{"targets":[{}]}},{"rasterizerState":{},"depthStencilState":{},"blendState":{"targets":[{}]}},{"rasterizerState":{},"depthStencilState":{},"blendState":{"targets":[{}]}}],[{"USE_TEXTURE":true},{},{}],[[[{},"mainTexture",6,0],{},{}],11,0,0]]],0,0,[0,0],[6,7],[15,2]],[[[17,"Egg 16B",[{"rasterizerState":{},"depthStencilState":{},"blendState":{"targets":[{}]}},{"rasterizerState":{},"depthStencilState":{},"blendState":{"targets":[{}]}},{"rasterizerState":{},"depthStencilState":{},"blendState":{"targets":[{}]}}],[{"USE_TEXTURE":true},{},{}],[[[{},"mainTexture",6,0],{},{}],11,0,0]]],0,0,[0,0],[6,7],[16,2]],[[[17,"Head",[{"rasterizerState":{},"depthStencilState":{},"blendState":{"targets":[{}]}},{"rasterizerState":{},"depthStencilState":{},"blendState":{"targets":[{}]}},{"rasterizerState":{},"depthStencilState":{},"blendState":{"targets":[{}]}}],[{"USE_TEXTURE":true},{},{}],[[[{},"mainTexture",6,0],{},{}],11,0,0]]],0,0,[0,0],[6,7],[17,2]],[[[19,"Role"],[26,"Role",[-41,-42,-43,-44,-45],[[13,-40,[8,"d7a3+3/hJN6YFSqUyFEGqZ"]]],[43,"c46/YsCPVOJYA4mWEpNYRx",null,-39,0,[[31,-36,[2,["acJk6yOi5Hx67v11gEOmkn"]],-35,[2,["acJk6yOi5Hx67v11gEOmkn"]]],[31,-38,[2,["bd2ap+dh1E+Lo2U66nNeOd"]],-37,[2,["bd2ap+dh1E+Lo2U66nNeOd"]]]],[-1,-2,-3,-4,-5,-6,-7,-8,-9,-10,-11,-12,-13,-14,-15,-16,-17,-18,-19,-20,-21,-22,-23,-24,-25,-26,-27,-28,-29,-30,-31,-32,-33,-34]]],[27,"Tail",1,[-47,-48,-49,-50,-51,-52,-53,-54,-55,-56,-57,-58,-59,-60,-61,-62,-63,-64,-65,-66],[[13,-46,[8,"a6WzKGGmZKAaZbqziZ5gC8"]]],[1,"9dG+jk6yhHvYDfN3is/ebO",null,null,null,1,0],[1,0,0,-3.018]],[20,"Role",1,[-67,-68,-69,-70,-71,-72,-73,-74,-75,-76,-77],[1,"4cqZBUnUpPbobxP7QOTYTm",null,null,null,1,0]],[5,0,{},3,[4,"4cSv7o5ahMHrusMuvKQ+VM",null,null,-82,[44,"385+tZo5RPBLLx/+dVv9Uv",1,[[3,"003",["_name"],-78],[0,["_lpos"],-79,[1,7.162,0,0]],[0,["_lrot"],-80,[3,0,0,0,1]],[0,["_euler"],-81,[1,0,0,0]]],[[2,["acJk6yOi5Hx67v11gEOmkn"]]]],2]],[2,["07HjaKrz5VuLD5nBiQgMRN"]],[2,["07HjaKrz5VuLD5nBiQgMRN"]],[2,["07HjaKrz5VuLD5nBiQgMRN"]],[2,["07HjaKrz5VuLD5nBiQgMRN"]],[2,["07HjaKrz5VuLD5nBiQgMRN"]],[2,["07HjaKrz5VuLD5nBiQgMRN"]],[2,["4cSv7o5ahMHrusMuvKQ+VM"]],[2,["e1JFFTY0hMBoxYEyevHvWM"]],[2,["42BzzzdaBO7Ju66ghMfHl4"]],[2,["4drnOZBk9FvqE77exqeEHW"]],[2,["fd3nuhnn1Frq+ykGmsZ6w/"]],[2,["7dJkqKp8JGvKimP7QD3ZCM"]],[2,["90Ma/1QSRBP698xnSupXrR"]],[2,["c2ylVluzpBObJ+p4gN8rbQ"]],[2,["34DMbEVgtK6qJpU0rWlG9Z"]],[2,["de4lHw+r9HirXbMHuphjX6"]],[2,["10gJH4rFxDYp2YxjR3t3RS"]],[2,["5eSkShuv1Ksq67LO8YjhAO"]],[2,["95b2CoIn1M6oJoeatZPQhl"]],[2,["04nC+smMdNx4tm1rcvG6P/"]],[2,["36RsbnTuZFbYWcr2kpk2pZ"]],[2,["78Irt40tRGFL8RU40zRLG6"]],[2,["d3PVx+WU1GF4ee8+unbz8c"]],[2,["a4Cct1nxtEvonO8p9DTO3G"]],[2,["d2vFRWbZpCWrKYTDXSZwFm"]],[2,["daziHBFeFHIr31uEYcBl8Z"]],[2,["7ak0XaDPtPmoGCnfh0XwJZ"]],[2,["0crJEXnBxOY7slUdG4YZvG"]],[2,["c1rpQAPAJK6YWsu+6eNS0p"]],[2,["66u+oXVStDcYGW2W0qQnj/"]],[2,["262keC1OBCvJrOA9CZ3d3E"]],[2,["195PoIxppP6aRYyeXvAvqG"]],[2,["01wMQNDnBPpY7P/5156nZ4"]],[2,["e8DyuTCfpJhJgq9AOw5YWd"]],[21,"m003",2,[-83,-84,-85],[1,"72QmVDIlZKrLAqU7E6LsGx",null,null,null,1,0],[1,68.815,0,-0.792]],[21,"m004",2,[-86,-87,-88],[1,"c6fUHH0+BCiZjsIMZKJZes",null,null,null,1,0],[1,72.329,0,-0.669]],[27,"Arrow",3,[-90],[[13,-89,[8,"89mNLAIRVFxr5M3BcHDJgm"]]],[1,"f2Adqo+OFI/ol1jYImHC4+",null,null,null,1,0],[1,7.162000000000035,0,0]],[5,0,{},3,[4,"e1JFFTY0hMBoxYEyevHvWM",null,null,-91,[6,"8acjAHN1xNV5Sk2cbyPRgH",1,[[3,"004",["_name"],12],[0,["_lpos"],12,[1,10.255,0,0]],[0,["_lrot"],12,[3,0,0,0,1]],[0,["_euler"],12,[1,0,0,0]]]],3]],[5,0,{},3,[4,"42BzzzdaBO7Ju66ghMfHl4",null,null,-92,[6,"b4Qy2iGnlB4r2/Kj4RU8yP",1,[[3,"009",["_name"],13],[0,["_lpos"],13,[1,28.878,0,0]],[0,["_lrot"],13,[3,0,0,0,1]],[0,["_euler"],13,[1,0,0,0]]]],4]],[5,0,{},3,[4,"4drnOZBk9FvqE77exqeEHW",null,null,-93,[6,"5a2rkByw9DcrAEaPN9tSEN",1,[[3,"011",["_name"],14],[0,["_lpos"],14,[1,34.623,0,0]],[0,["_lrot"],14,[3,0,0,0,1]],[0,["_euler"],14,[1,0,0,0]]]],5]],[5,0,{},3,[4,"fd3nuhnn1Frq+ykGmsZ6w/",null,null,-94,[6,"1e+e/XFp5KdovS0kS5O7vi",1,[[3,"015",["_name"],15],[0,["_lpos"],15,[1,49.003,0,0]],[0,["_lrot"],15,[3,0,0,0,1]],[0,["_euler"],15,[1,0,0,0]]]],6]],[5,0,{},3,[4,"7dJkqKp8JGvKimP7QD3ZCM",null,null,-95,[6,"3dVBMiW2NCn6EQENYRLGXI",1,[[3,"017",["_name"],16],[0,["_lpos"],16,[1,54.993,0,0]],[0,["_lrot"],16,[3,0,0,0,1]],[0,["_euler"],16,[1,0,0,0]]]],7]],[5,0,{},3,[4,"90Ma/1QSRBP698xnSupXrR",null,null,-96,[6,"adNeKTM2dEUrVf2kSw0C6y",1,[[3,"018",["_name"],17],[0,["_lpos"],17,[1,58.39,0,0]],[0,["_lrot"],17,[3,0,0,0,1]],[0,["_euler"],17,[1,0,0,0]]]],8]],[5,0,{},3,[4,"c2ylVluzpBObJ+p4gN8rbQ",null,null,-97,[6,"8cEZVzyO9Gfq1DI47bcTRD",1,[[3,"019",["_name"],18],[0,["_lpos"],18,[1,60.514,0,0]],[0,["_lrot"],18,[3,0,0,0,1]],[0,["_euler"],18,[1,0,0,0]]]],9]],[5,0,{},3,[4,"34DMbEVgtK6qJpU0rWlG9Z",null,null,-98,[6,"0eN6I2mHpFYbPxSP6rasNh",1,[[3,"020",["_name"],19],[0,["_lpos"],19,[1,62.512,0,0]],[0,["_lrot"],19,[3,0,0,0,1]],[0,["_euler"],19,[1,0,0,0]]]],10]],[5,0,{},3,[4,"de4lHw+r9HirXbMHuphjX6",null,null,-99,[6,"87EDJmM0dKnYtpMLI0XyW4",1,[[3,"021",["_name"],20],[0,["_lpos"],20,[1,64.904,0,0]],[0,["_lrot"],20,[3,0,0,0,1]],[0,["_euler"],20,[1,0,0,0]]]],11]],[5,0,{},2,[4,"10gJH4rFxDYp2YxjR3t3RS",null,null,-100,[6,"22yFE65hJJUr4n0cpkogsM",1,[[3,"003",["_name"],21],[0,["_lpos"],21,[1,6.078999999999951,0,-1]],[0,["_lrot"],21,[3,0,0,0,1]],[0,["_euler"],21,[1,0,0,0]],[10,["_lscale"],[2,["f6fTS8vIZBQYqrwq6oNAPo","55A3qkfHdfQruh0KKCuCWG"]],[1,1.5,1.5,1.5]],[9,["_materials","0"],[2,["f6fTS8vIZBQYqrwq6oNAPo","4fwF08KGdSrqV9Tx5vqSwp"]],13]]],12]],[5,0,{},2,[4,"5eSkShuv1Ksq67LO8YjhAO",null,null,-101,[6,"f3YWvA6clBXpMabEWwgzf1",1,[[3,"004",["_name"],22],[0,["_lpos"],22,[1,7.571000000000026,0,-1]],[0,["_lrot"],22,[3,0,0,0,1]],[0,["_euler"],22,[1,0,0,0]],[10,["_lscale"],[2,["29oNPJ0QtISbdmxmi6uZR5","55A3qkfHdfQruh0KKCuCWG"]],[1,1.5,1.5,1.5]],[9,["_materials","0"],[2,["29oNPJ0QtISbdmxmi6uZR5","4fwF08KGdSrqV9Tx5vqSwp"]],15]]],14]],[5,0,{},2,[4,"95b2CoIn1M6oJoeatZPQhl",null,null,-102,[6,"25V/IFuTJPqpCw/6U/LQb7",1,[[3,"006",["_name"],23],[0,["_lpos"],23,[1,10.456999999999994,0,-1]],[0,["_lrot"],23,[3,0,0,0,1]],[0,["_euler"],23,[1,0,0,0]],[10,["_lscale"],[2,["adZjsu+qNOs7P/BAm8qcCW","55A3qkfHdfQruh0KKCuCWG"]],[1,1.5,1.5,1.2]],[9,["_materials","0"],[2,["adZjsu+qNOs7P/BAm8qcCW","4fwF08KGdSrqV9Tx5vqSwp"]],17]]],16]],[5,0,{},2,[4,"04nC+smMdNx4tm1rcvG6P/",null,null,-103,[6,"3evobEnFpMPYFxsHk/UmSn",1,[[3,"007",["_name"],24],[0,["_lpos"],24,[1,12.353,0,-1]],[0,["_lrot"],24,[3,0,0,0,1]],[0,["_euler"],24,[1,0,0,0]],[10,["_lscale"],[2,["c2CsoIp/lKTayMgy98TWml","0dp/CnGvNRz6wd9CcFAwZr"]],[1,1.5,1.5,1.5]],[9,["_materials","0"],[2,["c2CsoIp/lKTayMgy98TWml","ddJVwn4H5ZTZfwx+fhAHbp"]],19]]],18]],[5,0,{},2,[4,"36RsbnTuZFbYWcr2kpk2pZ",null,null,-104,[6,"fflDgyKKRMk4wJLC8dHhpK",1,[[3,"015",["_name"],25],[0,["_lpos"],25,[1,15.159,0,-1]],[0,["_lrot"],25,[3,0,0,0,1]],[0,["_euler"],25,[1,0,0,0]],[10,["_lscale"],[2,["80Weym81BLuIJiKvIERr3r","f5mBtMOkZYyYIHOeZzce9r"]],[1,1.5,1.5,1.5]],[9,["_materials","0"],[2,["80Weym81BLuIJiKvIERr3r","79n2KvW0NRkoFzZjqkbKwt"]],21]]],20]],[5,0,{},2,[4,"78Irt40tRGFL8RU40zRLG6",null,null,-105,[6,"f2o4/vWlRNB7VKOuy+U9u+",1,[[3,"018",["_name"],26],[0,["_lpos"],26,[1,17.1,0,-1]],[0,["_lrot"],26,[3,0,0,0,1]],[0,["_euler"],26,[1,0,0,0]],[10,["_lscale"],[2,["990jAePx1HUIJcBVvag81C","f5mBtMOkZYyYIHOeZzce9r"]],[1,1.5,1.5,1.5]],[9,["_materials","0"],[2,["990jAePx1HUIJcBVvag81C","79n2KvW0NRkoFzZjqkbKwt"]],23]]],22]],[5,0,{},2,[4,"d3PVx+WU1GF4ee8+unbz8c",null,null,-106,[6,"8ezt2TfqpDCqMNVOu+17bB",1,[[3,"020",["_name"],27],[0,["_lpos"],27,[1,19.134,0,-1]],[0,["_lrot"],27,[3,0,0,0,1]],[0,["_euler"],27,[1,0,0,0]],[10,["_lscale"],[2,["4fDSOiyu1CPbTN1wZr129z","f5mBtMOkZYyYIHOeZzce9r"]],[1,1.5,1.5,1.5]],[9,["_materials","0"],[2,["4fDSOiyu1CPbTN1wZr129z","79n2KvW0NRkoFzZjqkbKwt"]],25]]],24]],[5,0,{},2,[4,"a4Cct1nxtEvonO8p9DTO3G",null,null,-107,[6,"45bBhTtUlGAoWkx+VaAD2B",1,[[3,"025",["_name"],28],[0,["_lpos"],28,[1,21.562,0,-1]],[0,["_lrot"],28,[3,0,0,0,1]],[0,["_euler"],28,[1,0,0,0]],[10,["_lscale"],[2,["5foYbaHl1BoYOjISGeDj6g","22EsLwDhdU8Js7ws/BgkG/"]],[1,1.5,1.5,1.5]],[9,["_materials","0"],[2,["5foYbaHl1BoYOjISGeDj6g","718Hfs4/5XFr8bGXTfcNxY"]],27]]],26]],[5,0,{},2,[4,"d2vFRWbZpCWrKYTDXSZwFm",null,null,-108,[6,"7a8+jiDxlNZaeJWt9D2S7C",1,[[3,"028",["_name"],29],[0,["_lpos"],29,[1,24.491,0,-1]],[0,["_lrot"],29,[3,0,0,0,1]],[0,["_euler"],29,[1,0,0,0]],[10,["_lscale"],[2,["6de1R8hhlAwrC7caIdDv80","22EsLwDhdU8Js7ws/BgkG/"]],[1,1.5,1.5,1.5]],[9,["_materials","0"],[2,["6de1R8hhlAwrC7caIdDv80","718Hfs4/5XFr8bGXTfcNxY"]],29]]],28]],[5,0,{},2,[4,"daziHBFeFHIr31uEYcBl8Z",null,null,-109,[6,"31lNlng+tORZxwd6kbZs7D",1,[[3,"036",["_name"],30],[0,["_lpos"],30,[1,29.751,0,-1]],[0,["_lrot"],30,[3,0,0,0,1]],[0,["_euler"],30,[1,0,0,0]],[10,["_lscale"],[2,["3ftuziYIRPq4gxL0jX8hfT","a5SpmOLTtRz6CnSRhHLl6M"]],[1,1.5,1.5,1.5]],[9,["_materials","0"],[2,["3ftuziYIRPq4gxL0jX8hfT","1fiFg1U8FeI7f7AquRltHM"]],31]]],30]],[5,0,{},2,[4,"7ak0XaDPtPmoGCnfh0XwJZ",null,null,-110,[6,"12NZeBQgxE66GRYeulBzwb",1,[[3,"044",["_name"],31],[0,["_lpos"],31,[1,34.723,0,-1]],[0,["_lrot"],31,[3,0,0,0,1]],[0,["_euler"],31,[1,0,0,0]],[10,["_lscale"],[2,["faMJ2CCh5A5YjmgLEO+qdc","07HjaKrz5VuLD5nBiQgMRN"]],[1,1.5,1.5,1.5]],[9,["_materials","0"],[2,["faMJ2CCh5A5YjmgLEO+qdc","30bS4+vV5WaLmEqHda2SPp"]],33]]],32]],[5,0,{},2,[4,"0crJEXnBxOY7slUdG4YZvG",null,null,-111,[6,"89U5NIvglHPqG1gUQd2ryo",1,[[3,"045",["_name"],32],[0,["_lpos"],32,[1,38.343,0,-1]],[0,["_lrot"],32,[3,0,0,0,1]],[0,["_euler"],32,[1,0,0,0]],[10,["_lscale"],[2,["c33WGuW9FPXZpabAUaxJNK","07HjaKrz5VuLD5nBiQgMRN"]],[1,1.5,1.5,1.5]],[9,["_materials","0"],[2,["c33WGuW9FPXZpabAUaxJNK","30bS4+vV5WaLmEqHda2SPp"]],35]]],34]],[5,0,{},2,[4,"c1rpQAPAJK6YWsu+6eNS0p",null,null,-112,[6,"fbwjCcWzRLXqRktCk9uW4A",1,[[3,"046",["_name"],33],[0,["_lpos"],33,[1,42.636,0,-1]],[0,["_lrot"],33,[3,0,0,0,1]],[0,["_euler"],33,[1,0,0,0]],[10,["_lscale"],[2,["98DB9we2hHNYfEXLDSraJM","07HjaKrz5VuLD5nBiQgMRN"]],[1,1.5,1.5,1.5]],[9,["_materials","0"],[2,["98DB9we2hHNYfEXLDSraJM","30bS4+vV5WaLmEqHda2SPp"]],37]]],36]],[5,0,{},2,[4,"66u+oXVStDcYGW2W0qQnj/",null,null,-113,[6,"a1ZSzAaaZBQIc/60GdxPB4",1,[[3,"048",["_name"],34],[0,["_lpos"],34,[1,46.82,0,-1]],[0,["_lrot"],34,[3,0,0,0,1]],[0,["_euler"],34,[1,0,0,0]],[10,["_lscale"],[2,["44pZcgawxBxJFsxQTKqqQa","07HjaKrz5VuLD5nBiQgMRN"]],[1,1.5,1.5,1.5]],[9,["_materials","0"],[2,["44pZcgawxBxJFsxQTKqqQa","30bS4+vV5WaLmEqHda2SPp"]],39]]],38]],[5,0,{},2,[4,"262keC1OBCvJrOA9CZ3d3E",null,null,-114,[6,"59EoWVQAtCmKGK6nU9Ri6R",1,[[3,"063",["_name"],35],[0,["_lpos"],35,[1,51.719,0,-1]],[0,["_lrot"],35,[3,0,0,0,1]],[0,["_euler"],35,[1,0,0,0]],[9,["_materials","0"],[2,["fexIQg6uJBM7PpnfTJE7Xn","cblJGwehBd0pp9L/y8wXS/"]],41],[10,["_lscale"],[2,["fexIQg6uJBM7PpnfTJE7Xn","fbqRYEe2Zdl4I8fowWbJAK"]],[1,1.5,1.5,1.5]]]],40]],[5,0,{},2,[4,"195PoIxppP6aRYyeXvAvqG",null,null,-115,[6,"73LZS3m9JGJLrsn6l7twGj",1,[[3,"064",["_name"],36],[0,["_lpos"],36,[1,56.009,0,-1]],[0,["_lrot"],36,[3,0,0,0,1]],[0,["_euler"],36,[1,0,0,0]],[9,["_materials","0"],[2,["ebh95GeOVLu4kM44WQjJzg","cblJGwehBd0pp9L/y8wXS/"]],43],[10,["_lscale"],[2,["ebh95GeOVLu4kM44WQjJzg","fbqRYEe2Zdl4I8fowWbJAK"]],[1,1.5,1.5,1.5]]]],42]],[5,0,{},2,[4,"01wMQNDnBPpY7P/5156nZ4",null,null,-116,[6,"19xjGlQh5GZrD+VPoLOpW5",1,[[3,"065",["_name"],37],[0,["_lpos"],37,[1,60.889,0,-1]],[0,["_lrot"],37,[3,0,0,0,1]],[0,["_euler"],37,[1,0,0,0]],[9,["_materials","0"],[2,["20aNE5waBIaJ2a60xZ0tmo","cblJGwehBd0pp9L/y8wXS/"]],45],[10,["_lscale"],[2,["20aNE5waBIaJ2a60xZ0tmo","fbqRYEe2Zdl4I8fowWbJAK"]],[1,1.5,1.5,1.5]]]],44]],[5,0,{},2,[4,"e8DyuTCfpJhJgq9AOw5YWd",null,null,-117,[6,"709PGf5QhEcJbWnO4ZPpQN",1,[[3,"m001",["_name"],38],[0,["_lpos"],38,[1,65.484,0,-1]],[0,["_lrot"],38,[3,0,0,0,1]],[0,["_euler"],38,[1,0,0,0]],[10,["_lpos"],[2,["53Q98SIMpF45Pw9IVR7D5K"]],[1,0,0,-2.019]]]],46]],[20,"Section-003",39,[-118,-119],[1,"51Ye1UyexB07TPNbsjx9my",null,null,null,1,0]],[18,"Main",69,[-121],[[13,-120,[8,"0eI3LE+cJFo5oxOdi5N+2R"]]],[1,"25ipvPvbBBT5qxyqZX34kF",null,null,null,1,0]],[5,0,{},70,[4,"07HjaKrz5VuLD5nBiQgMRN",null,null,-122,[6,"d9lGYACXFAEKK8iU2nkFni",1,[[3,"Egg Spike",["_name"],5],[0,["_lpos"],5,[1,0,0,0]],[0,["_lrot"],5,[3,0,0,0,1]],[0,["_euler"],5,[1,0,0,0]],[0,["_lscale"],5,[1,1.5,1.5,1.5]],[9,["_materials","0"],[2,["30bS4+vV5WaLmEqHda2SPp"]],50]]],49]],[21,"Section-001",39,[-123,-124],[1,"8cAljjf0NK7qKyZOAS6Mkj",null,null,null,1,0],[1,0,0,-1.597]],[18,"Main",72,[-126],[[13,-125,[8,"83XUGWMdJGqb+v3sCjcr1Q"]]],[1,"fcansBZLJHfJg9ZNlzs+aC",null,null,null,1,0]],[5,0,{},73,[4,"07HjaKrz5VuLD5nBiQgMRN",null,null,-127,[6,"bf+Mry0MZMiZ7UsA60H1nB",1,[[3,"Egg Spike",["_name"],6],[0,["_lpos"],6,[1,0,0,0]],[0,["_lrot"],6,[3,0,0,0,1]],[0,["_euler"],6,[1,0,0,0]],[0,["_lscale"],6,[1,1.5,1.5,1.5]],[9,["_materials","0"],[2,["30bS4+vV5WaLmEqHda2SPp"]],54]]],53]],[21,"Section",39,[-128,-129],[1,"e2pCQKhZxCIaT/rKqyZrs8",null,null,null,1,0],[1,0,0,-3.287]],[18,"Main",75,[-131],[[13,-130,[8,"dcj+SCmKJGramxtfqV8gyx"]]],[1,"41eUJbu8xLxL5CA7nO8Ztp",null,null,null,1,0]],[5,0,{},76,[4,"07HjaKrz5VuLD5nBiQgMRN",null,null,-132,[6,"a9KQOjM3RAa5bVxUeRGedl",1,[[3,"Egg Spike",["_name"],7],[0,["_lpos"],7,[1,0,0,0]],[0,["_lrot"],7,[3,0,0,0,1]],[0,["_euler"],7,[1,0,0,0]],[0,["_lscale"],7,[1,1.5,1.5,1.5]],[9,["_materials","0"],[2,["30bS4+vV5WaLmEqHda2SPp"]],58]]],57]],[20,"Section",40,[-133,-134],[1,"53bIHg0S9Fqq8+naNhXZ+8",null,null,null,1,0]],[18,"Main",78,[-136],[[13,-135,[8,"92XgmNjg1DD6riJqI+rlk7"]]],[1,"a0qbU4DhNMb5zgUycr9FVi",null,null,null,1,0]],[5,0,{},79,[4,"07HjaKrz5VuLD5nBiQgMRN",null,null,-137,[6,"f1wtVKJhhJ7oiG3SLKNk5q",1,[[3,"Egg Spike",["_name"],8],[0,["_lpos"],8,[1,0,0,0]],[0,["_lrot"],8,[3,0,0,0,1]],[0,["_euler"],8,[1,0,0,0]],[0,["_lscale"],8,[1,1.5,1.5,1.5]],[9,["_materials","0"],[2,["30bS4+vV5WaLmEqHda2SPp"]],62]]],61]],[21,"Section-001",40,[-138,-139],[1,"93YSOR0MhMapRIGLS8MJne",null,null,null,1,0],[1,0,0,-2.228]],[18,"Main",81,[-141],[[13,-140,[8,"73cF3vdRBHzbZE20lBHHTx"]]],[1,"c8zXeACI5B96mb9zqy8J7a",null,null,null,1,0]],[5,0,{},82,[4,"07HjaKrz5VuLD5nBiQgMRN",null,null,-142,[6,"2dn4yEx6xBU5eVuU2C5jxh",1,[[3,"Egg Spike",["_name"],9],[0,["_lpos"],9,[1,0,0,0]],[0,["_lrot"],9,[3,0,0,0,1]],[0,["_euler"],9,[1,0,0,0]],[0,["_lscale"],9,[1,1.5,1.5,1.5]],[9,["_materials","0"],[2,["30bS4+vV5WaLmEqHda2SPp"]],66]]],65]],[21,"Section-002",40,[-143,-144],[1,"30/wSlJ/1OVJerFVWXgq6L",null,null,null,1,0],[1,0,0,-4.614]],[18,"Main",84,[-146],[[13,-145,[8,"b2whkGoDxICrSGLOtdMzwi"]]],[1,"a9vxBQEeFOS4mhZDV832J+",null,null,null,1,0]],[5,0,{},85,[4,"07HjaKrz5VuLD5nBiQgMRN",null,null,-147,[6,"15pF1Mxv9I/aau0Lam3RDV",1,[[3,"Egg Spike",["_name"],10],[0,["_lpos"],10,[1,0,0,0]],[0,["_lrot"],10,[3,0,0,0,1]],[0,["_euler"],10,[1,0,0,0]],[0,["_lscale"],10,[1,1.5,1.5,1.5]],[9,["_materials","0"],[2,["30bS4+vV5WaLmEqHda2SPp"]],70]]],69]],[24,"RoleCollision",1,[[25,true,1.5,-148,[8,"d37tNBek1PkrYdNGqoFlzi"]],[36,2,false,-149,[8,"bd2ap+dh1E+Lo2U66nNeOd"]]],[1,"695KQ63jtMZ4AqS/QVjpgO",null,null,null,1,0],[1,7.162000000000035,0,0]],[24,"RoleCollisionEat",1,[[25,true,3,-150,[8,"bb5kcSQBBLkamtWNULKcpC"]],[36,16,false,-151,[8,"51Fjb+V91APJLwmSZpl5+O"]]],[1,"36owaV8A9Aq7lLYXcS8xB2",null,null,null,1,0],[1,7.162000000000035,0,0]],[24,"TailCollision",1,[[25,true,0.8,-152,[8,"67XItV4IBKR5MZGHRtP4IR"]],[46,4,2,-153,[8,"b6ub0kz0xNT50v6cNPLW/x"]]],[1,"59JU8DQ/JOkbM5VinI0qaw",null,null,null,1,0],[1,6.063,0,-3.963]],[40,"Arrow",41,[[14,"Quad<ModelComponent>",-154,[8,"7d7nxGjbZKf5yJdaKW/TfN"],[0],[15],1]],[1,"6bEauEoNxDnrI5W1BAX5tU",null,null,null,1,0],[1,0,0,2.236],[3,-0.5,0.5,0.4999999999999999,0.5000000000000001],[1,1.5,2,1],[1,-89.99999999999999,89.99999999999999,0]],[16,"Shadow",69,[[14,"Quad<ModelComponent>",-155,[8,"72TNaFuEZMr5VuFdS1K/aH"],[47],[15],48]],[1,"f1lAh8zgFB+ae2KaZEiOVV",null,null,null,1,0],[3,-0.7071067811865475,0,0,0.7071067811865476],[1,3,3,1],[1,-90,0,0]],[16,"Shadow",72,[[14,"Quad<ModelComponent>",-156,[8,"85uobtN5NObYrfT9GyLx85"],[51],[15],52]],[1,"03+gAfu7ZEppsB27dx5tdT",null,null,null,1,0],[3,-0.7071067811865475,0,0,0.7071067811865476],[1,3,3,1],[1,-90,0,0]],[16,"Shadow",75,[[14,"Quad<ModelComponent>",-157,[8,"958VtpNRtG0K2yM4F15dML"],[55],[15],56]],[1,"83wSS2xN5EC4BBpSuWH9OR",null,null,null,1,0],[3,-0.7071067811865475,0,0,0.7071067811865476],[1,3,3,1],[1,-90,0,0]],[16,"Shadow",78,[[14,"Quad<ModelComponent>",-158,[8,"4bV978NrFCA693rhKbcr2d"],[59],[15],60]],[1,"78RzP+j2tK8rJbCQciOOB5",null,null,null,1,0],[3,-0.7071067811865475,0,0,0.7071067811865476],[1,3,3,1],[1,-90,0,0]],[16,"Shadow",81,[[14,"Quad<ModelComponent>",-159,[8,"d0HMgzFphJqLOnw1+5ZlOr"],[63],[15],64]],[1,"76+x6/tK1L7ou0cpyVUhQL",null,null,null,1,0],[3,-0.7071067811865475,0,0,0.7071067811865476],[1,3,3,1],[1,-90,0,0]],[16,"Shadow",84,[[14,"Quad<ModelComponent>",-160,[8,"e0bSYZnltI2YXjIfD1s8pY"],[67],[15],68]],[1,"5cyZ1aV4BKsbJNcupNygjo",null,null,null,1,0],[3,-0.7071067811865475,0,0,0.7071067811865476],[1,3,3,1],[1,-90,0,0]]],0,[0,-1,86,0,-2,83,0,-3,80,0,-4,77,0,-5,74,0,-6,71,0,-7,68,0,-8,67,0,-9,66,0,-10,65,0,-11,64,0,-12,63,0,-13,62,0,-14,61,0,-15,60,0,-16,59,0,-17,58,0,-18,57,0,-19,56,0,-20,55,0,-21,54,0,-22,53,0,-23,52,0,-24,51,0,-25,50,0,-26,49,0,-27,48,0,-28,47,0,-29,46,0,-30,45,0,-31,44,0,-32,43,0,-33,42,0,-34,4,0,10,4,0,11,4,0,10,4,0,11,4,0,0,1,0,2,1,0,-1,3,0,-2,2,0,-3,87,0,-4,88,0,-5,89,0,2,2,0,-1,51,0,-2,52,0,-3,53,0,-4,54,0,-5,55,0,-6,56,0,-7,57,0,-8,58,0,-9,59,0,-10,60,0,-11,61,0,-12,62,0,-13,63,0,-14,64,0,-15,65,0,-16,66,0,-17,67,0,-18,68,0,-19,39,0,-20,40,0,-1,41,0,-2,4,0,-3,42,0,-4,43,0,-5,44,0,-6,45,0,-7,46,0,-8,47,0,-9,48,0,-10,49,0,-11,50,0,8,11,0,8,11,0,8,11,0,8,11,0,0,4,0,-1,69,0,-2,72,0,-3,75,0,-1,78,0,-2,81,0,-3,84,0,2,41,0,-1,90,0,0,42,0,0,43,0,0,44,0,0,45,0,0,46,0,0,47,0,0,48,0,0,49,0,0,50,0,0,51,0,0,52,0,0,53,0,0,54,0,0,55,0,0,56,0,0,57,0,0,58,0,0,59,0,0,60,0,0,61,0,0,62,0,0,63,0,0,64,0,0,65,0,0,66,0,0,67,0,0,68,0,-1,91,0,-2,70,0,2,70,0,-1,71,0,0,71,0,-1,92,0,-2,73,0,2,73,0,-1,74,0,0,74,0,-1,93,0,-2,76,0,2,76,0,-1,77,0,0,77,0,-1,94,0,-2,79,0,2,79,0,-1,80,0,0,80,0,-1,95,0,-2,82,0,2,82,0,-1,83,0,0,83,0,-1,96,0,-2,85,0,2,85,0,-1,86,0,0,86,0,2,87,0,2,87,0,2,88,0,2,88,0,2,89,0,2,89,0,2,90,0,2,91,0,2,92,0,2,93,0,2,94,0,2,95,0,2,96,0,9,1,160],[0,0,0,0,0,0,0,0,0,0,0,0,0,0,0,0,0,0,0,0,0,0,0,0,0,0,0,0,0,0,0,0,0,0,0,0,0,0,0,0,0,0,0,0,0,0,0,0,0,0,0,0,0,0,0,0,0,0,0,0,0,0,0,0,0,0,0,0,0,0,0],[-1,5,1,1,1,1,1,1,1,1,1,1,1,3,1,3,1,3,1,3,1,3,1,3,1,3,1,3,1,3,1,3,1,3,1,3,1,3,1,3,1,3,1,3,1,3,1,-1,5,1,3,-1,5,1,3,-1,5,1,3,-1,5,1,3,-1,5,1,3,-1,5,1,3],[18,0,19,20,21,22,23,24,25,26,27,28,29,30,31,5,32,33,34,35,36,6,37,38,39,40,41,42,43,44,45,46,47,48,49,50,51,4,52,7,53,54,55,8,56,57,58,1,0,3,9,1,0,3,9,1,0,3,59,1,0,3,4,1,0,3,4,1,0,3,7]],[[[19,"004"],[22,"004",[-3],[23,"5eSkShuv1Ksq67LO8YjhAO",null,null,-2,0,[-1]],[1,7.571000000000026,0,-1]],[2,["55A3qkfHdfQruh0KKCuCWG"]],[20,"Section",1,[-4,-5],[1,"f2uJNXi+BKo4jcgKmSFDOL",null,null,null,1,0]],[18,"Main",3,[-7],[[13,-6,[8,"f8IUusAr1L5bSc0irU1GTC"]]],[1,"37Nl4q7YVL74ZQNdqNp5hz",null,null,null,1,0]],[5,0,{},4,[4,"55A3qkfHdfQruh0KKCuCWG",null,null,-8,[6,"29oNPJ0QtISbdmxmi6uZR5",1,[[3,"Egg Horn",["_name"],2],[0,["_lpos"],2,[1,0,0,0]],[0,["_lrot"],2,[3,0,0,0,1]],[0,["_euler"],2,[1,0,0,0]],[0,["_lscale"],2,[1,1.5,1.5,1.5]],[9,["_materials","0"],[2,["4fwF08KGdSrqV9Tx5vqSwp"]],3]]],2]],[16,"Shadow",3,[[14,"Quad<ModelComponent>",-9,[8,"35HpllgUpJnr0eR7H3CKR1"],[0],[15],1]],[1,"20UPqLUoBAwLEoUwvmEHrY",null,null,null,1,0],[3,-0.7071067811865475,0,0,0.7071067811865476],[1,3,3,1],[1,-90,0,0]]],0,[0,-1,5,0,0,1,0,-1,3,0,-1,6,0,-2,4,0,2,4,0,-1,5,0,0,5,0,2,6,0,9,1,9],[0,0,0,0],[-1,5,1,3],[1,0,60,5]],[[[19,"015"],[22,"015",[-3],[23,"36RsbnTuZFbYWcr2kpk2pZ",null,null,-2,0,[-1]],[1,26.925,0,-1]],[2,["f5mBtMOkZYyYIHOeZzce9r"]],[20,"Section",1,[-4,-5],[1,"bexBmRSORK1b6xXEM8fLND",null,null,null,1,0]],[18,"Main",3,[-7],[[13,-6,[8,"c3agYqjIFEfZFHcQm21QTb"]]],[1,"f0LEppWsFCyrlWoFuOMUy5",null,null,null,1,0]],[5,0,{},4,[4,"f5mBtMOkZYyYIHOeZzce9r",null,null,-8,[6,"80Weym81BLuIJiKvIERr3r",1,[[3,"Egg",["_name"],2],[0,["_lpos"],2,[1,0,0,0]],[0,["_lrot"],2,[3,0,0,0,1]],[0,["_euler"],2,[1,0,0,0]],[0,["_lscale"],2,[1,1.5,1.5,1.5]],[9,["_materials","0"],[2,["79n2KvW0NRkoFzZjqkbKwt"]],3]]],2]],[16,"Shadow",3,[[14,"Quad<ModelComponent>",-9,[8,"e4izaW9gxETLhn7Av4wmxn"],[0],[15],1]],[1,"5675xDWT9NBowdqqN9gRxK",null,null,null,1,0],[3,-0.7071067811865475,0,0,0.7071067811865476],[1,3,3,1],[1,-90,0,0]]],0,[0,-1,5,0,0,1,0,-1,3,0,-1,6,0,-2,4,0,2,4,0,-1,5,0,0,5,0,2,6,0,9,1,9],[0,0,0,0],[-1,5,1,3],[1,0,61,6]],[[[17,"Egg 06E",[{"rasterizerState":{},"depthStencilState":{},"blendState":{"targets":[{}]}},{"rasterizerState":{},"depthStencilState":{},"blendState":{"targets":[{}]}},{"rasterizerState":{},"depthStencilState":{},"blendState":{"targets":[{}]}}],[{"USE_INSTANCING":true,"USE_TEXTURE":true},{},{}],[[[{},"mainTexture",6,0],{},{}],11,0,0]]],0,0,[0,0],[6,7],[62,2]],[[[19,"064"],[22,"064",[-3],[23,"195PoIxppP6aRYyeXvAvqG",null,null,-2,0,[-1]],[1,137.102,0,-1]],[2,["fbqRYEe2Zdl4I8fowWbJAK"]],[20,"Section",1,[-4,-5],[1,"091pQbeexHdrqSgnR9zhL4",null,null,null,1,0]],[18,"Main",3,[-7],[[13,-6,[8,"403k1prw9NF6YqibVexD20"]]],[1,"a5O2Ao5QJGzbu3us/wkf1e",null,null,null,1,0]],[5,0,{},4,[4,"fbqRYEe2Zdl4I8fowWbJAK",null,null,-8,[6,"ebh95GeOVLu4kM44WQjJzg",1,[[3,"Egg Wings",["_name"],2],[0,["_lpos"],2,[1,0,0,0]],[0,["_lrot"],2,[3,0,0,0,1]],[0,["_euler"],2,[1,0,0,0]],[9,["_materials","0"],[2,["cblJGwehBd0pp9L/y8wXS/"]],3],[0,["_lscale"],2,[1,1.5,1.5,1.5]]]],2]],[16,"Shadow",3,[[14,"Quad<ModelComponent>",-9,[8,"89VHjjXdFLBJo9zw+KHQmj"],[0],[15],1]],[1,"a7uWu2OCtLLbKp7L8EM1zA",null,null,null,1,0],[3,-0.7071067811865475,0,0,0.7071067811865476],[1,3,3,1],[1,-90,0,0]]],0,[0,-1,5,0,0,1,0,-1,3,0,-1,6,0,-2,4,0,2,4,0,-1,5,0,0,5,0,2,6,0,9,1,9],[0,0,0,0],[-1,5,1,3],[1,0,63,8]],[[[19,"018"],[22,"018",[-3,-4],[23,"90Ma/1QSRBP698xnSupXrR",null,null,-2,0,[-1]],[1,58.39,0,0]],[2,["13Qf0bJqFWoaygghgquMcT"]],[28,0,{},[4,"45UDS+VRRYaKfpI+U/RcFZ",null,null,-12,[32,"e1ah8rB0BII6YxBetKN5pi",1,[[37,[2,["45UDS+VRRYaKfpI+U/RcFZ"]],[[38,-11,[8,"bcVY5OXjhJpL11vuZt718K"],1]]]],[[3,"苏尔",["_name"],-5],[0,["_lpos"],-6,[1,0,0,0]],[0,["_lrot"],-7,[3,0,0,0,1]],[0,["_euler"],-8,[1,0,0,0]],[33,["_materials","0"],2,2],[45,["_skinningRoot"],2,-9],[3,2,["_materials","length"],2],[33,["_materials","1"],2,3],[34,true,["_active"],[2,["34XuBURsVRfKVYrCe0nmXr"]]],[0,["_lscale"],-10,[1,1,1,1]],[3,1,["_shadowCastingMode"],2],[3,1,["_shadowReceivingMode"],2]],[[2,["40HcGhz9pRqpl99HSp8+c1"]]]],0]],[2,["45UDS+VRRYaKfpI+U/RcFZ"]],[29,"Main",1,[3],[1,"9203xYDAVBi453nv1lSSMT",null,null,null,1,0],[1,2,2,2]],[16,"Shadow",1,[[14,"Quad<ModelComponent>",-13,[8,"6c6p9LrjNHgrk12fAljx8x"],[4],[15],5]],[1,"6cHr5m+S5Ne6dZA08Qb28u",null,null,null,1,0],[3,-0.7071067811865475,0,0,0.7071067811865476],[1,3,3,1],[1,-89.99999999999999,0,0]]],0,[0,-1,3,0,0,1,0,-1,5,0,-2,6,0,8,4,0,8,4,0,8,4,0,8,4,0,3,3,0,8,4,0,2,3,0,0,3,0,2,6,0,9,1,3,4,5,13],[0,0,0,0,0,0],[1,12,3,3,-1,5],[64,65,66,67,1,0]],[[[17,"Egg 01B",[{"rasterizerState":{},"depthStencilState":{},"blendState":{"targets":[{}]}},{"rasterizerState":{},"depthStencilState":{},"blendState":{"targets":[{}]}},{"rasterizerState":{},"depthStencilState":{},"blendState":{"targets":[{}]}}],[{"USE_TEXTURE":true},{},{}],[[[{},"mainTexture",6,0],{},{}],11,0,0]]],0,0,[0,0],[6,7],[68,2]],[[[48,"Skin-0",3742927262,["关节/mixamorig_Hips","关节/mixamorig_Hips/mixamorig_Spine","关节/mixamorig_Hips/mixamorig_Spine/mixamorig_Spine1","关节/mixamorig_Hips/mixamorig_Spine/mixamorig_Spine1/mixamorig_Spine2","关节/mixamorig_Hips/mixamorig_Spine/mixamorig_Spine1/mixamorig_Spine2/mixamorig_Neck","关节/mixamorig_Hips/mixamorig_Spine/mixamorig_Spine1/mixamorig_Spine2/mixamorig_Neck/mixamorig_Head","关节/mixamorig_Hips/mixamorig_Spine/mixamorig_Spine1/mixamorig_Spine2/mixamorig_Neck/mixamorig_Head/mixamorig_HeadTop_End","关节/mixamorig_Hips/mixamorig_Spine/mixamorig_Spine1/mixamorig_Spine2/mixamorig_LeftShoulder","关节/mixamorig_Hips/mixamorig_Spine/mixamorig_Spine1/mixamorig_Spine2/mixamorig_LeftShoulder/mixamorig_LeftArm","关节/mixamorig_Hips/mixamorig_Spine/mixamorig_Spine1/mixamorig_Spine2/mixamorig_LeftShoulder/mixamorig_LeftArm/mixamorig_LeftForeArm","关节/mixamorig_Hips/mixamorig_Spine/mixamorig_Spine1/mixamorig_Spine2/mixamorig_LeftShoulder/mixamorig_LeftArm/mixamorig_LeftForeArm/mixamorig_LeftHand","关节/mixamorig_Hips/mixamorig_Spine/mixamorig_Spine1/mixamorig_Spine2/mixamorig_LeftShoulder/mixamorig_LeftArm/mixamorig_LeftForeArm/mixamorig_LeftHand/mixamorig_LeftHandThumb1","关节/mixamorig_Hips/mixamorig_Spine/mixamorig_Spine1/mixamorig_Spine2/mixamorig_LeftShoulder/mixamorig_LeftArm/mixamorig_LeftForeArm/mixamorig_LeftHand/mixamorig_LeftHandThumb1/mixamorig_LeftHandThumb2","关节/mixamorig_Hips/mixamorig_Spine/mixamorig_Spine1/mixamorig_Spine2/mixamorig_LeftShoulder/mixamorig_LeftArm/mixamorig_LeftForeArm/mixamorig_LeftHand/mixamorig_LeftHandThumb1/mixamorig_LeftHandThumb2/mixamorig_LeftHandThumb3","关节/mixamorig_Hips/mixamorig_Spine/mixamorig_Spine1/mixamorig_Spine2/mixamorig_LeftShoulder/mixamorig_LeftArm/mixamorig_LeftForeArm/mixamorig_LeftHand/mixamorig_LeftHandThumb1/mixamorig_LeftHandThumb2/mixamorig_LeftHandThumb3/mixamorig_LeftHandThumb4","关节/mixamorig_Hips/mixamorig_Spine/mixamorig_Spine1/mixamorig_Spine2/mixamorig_LeftShoulder/mixamorig_LeftArm/mixamorig_LeftForeArm/mixamorig_LeftHand/mixamorig_LeftHandIndex1","关节/mixamorig_Hips/mixamorig_Spine/mixamorig_Spine1/mixamorig_Spine2/mixamorig_LeftShoulder/mixamorig_LeftArm/mixamorig_LeftForeArm/mixamorig_LeftHand/mixamorig_LeftHandIndex1/mixamorig_LeftHandIndex2","关节/mixamorig_Hips/mixamorig_Spine/mixamorig_Spine1/mixamorig_Spine2/mixamorig_LeftShoulder/mixamorig_LeftArm/mixamorig_LeftForeArm/mixamorig_LeftHand/mixamorig_LeftHandIndex1/mixamorig_LeftHandIndex2/mixamorig_LeftHandIndex3","关节/mixamorig_Hips/mixamorig_Spine/mixamorig_Spine1/mixamorig_Spine2/mixamorig_LeftShoulder/mixamorig_LeftArm/mixamorig_LeftForeArm/mixamorig_LeftHand/mixamorig_LeftHandIndex1/mixamorig_LeftHandIndex2/mixamorig_LeftHandIndex3/mixamorig_LeftHandIndex4","关节/mixamorig_Hips/mixamorig_Spine/mixamorig_Spine1/mixamorig_Spine2/mixamorig_LeftShoulder/mixamorig_LeftArm/mixamorig_LeftForeArm/mixamorig_LeftHand/mixamorig_LeftHandMiddle1","关节/mixamorig_Hips/mixamorig_Spine/mixamorig_Spine1/mixamorig_Spine2/mixamorig_LeftShoulder/mixamorig_LeftArm/mixamorig_LeftForeArm/mixamorig_LeftHand/mixamorig_LeftHandMiddle1/mixamorig_LeftHandMiddle2","关节/mixamorig_Hips/mixamorig_Spine/mixamorig_Spine1/mixamorig_Spine2/mixamorig_LeftShoulder/mixamorig_LeftArm/mixamorig_LeftForeArm/mixamorig_LeftHand/mixamorig_LeftHandMiddle1/mixamorig_LeftHandMiddle2/mixamorig_LeftHandMiddle3","关节/mixamorig_Hips/mixamorig_Spine/mixamorig_Spine1/mixamorig_Spine2/mixamorig_LeftShoulder/mixamorig_LeftArm/mixamorig_LeftForeArm/mixamorig_LeftHand/mixamorig_LeftHandMiddle1/mixamorig_LeftHandMiddle2/mixamorig_LeftHandMiddle3/mixamorig_LeftHandMiddle4","关节/mixamorig_Hips/mixamorig_Spine/mixamorig_Spine1/mixamorig_Spine2/mixamorig_LeftShoulder/mixamorig_LeftArm/mixamorig_LeftForeArm/mixamorig_LeftHand/mixamorig_LeftHandRing1","关节/mixamorig_Hips/mixamorig_Spine/mixamorig_Spine1/mixamorig_Spine2/mixamorig_LeftShoulder/mixamorig_LeftArm/mixamorig_LeftForeArm/mixamorig_LeftHand/mixamorig_LeftHandRing1/mixamorig_LeftHandRing2","关节/mixamorig_Hips/mixamorig_Spine/mixamorig_Spine1/mixamorig_Spine2/mixamorig_LeftShoulder/mixamorig_LeftArm/mixamorig_LeftForeArm/mixamorig_LeftHand/mixamorig_LeftHandRing1/mixamorig_LeftHandRing2/mixamorig_LeftHandRing3","关节/mixamorig_Hips/mixamorig_Spine/mixamorig_Spine1/mixamorig_Spine2/mixamorig_LeftShoulder/mixamorig_LeftArm/mixamorig_LeftForeArm/mixamorig_LeftHand/mixamorig_LeftHandRing1/mixamorig_LeftHandRing2/mixamorig_LeftHandRing3/mixamorig_LeftHandRing4","关节/mixamorig_Hips/mixamorig_Spine/mixamorig_Spine1/mixamorig_Spine2/mixamorig_LeftShoulder/mixamorig_LeftArm/mixamorig_LeftForeArm/mixamorig_LeftHand/mixamorig_LeftHandPinky1","关节/mixamorig_Hips/mixamorig_Spine/mixamorig_Spine1/mixamorig_Spine2/mixamorig_LeftShoulder/mixamorig_LeftArm/mixamorig_LeftForeArm/mixamorig_LeftHand/mixamorig_LeftHandPinky1/mixamorig_LeftHandPinky2","关节/mixamorig_Hips/mixamorig_Spine/mixamorig_Spine1/mixamorig_Spine2/mixamorig_LeftShoulder/mixamorig_LeftArm/mixamorig_LeftForeArm/mixamorig_LeftHand/mixamorig_LeftHandPinky1/mixamorig_LeftHandPinky2/mixamorig_LeftHandPinky3","关节/mixamorig_Hips/mixamorig_Spine/mixamorig_Spine1/mixamorig_Spine2/mixamorig_LeftShoulder/mixamorig_LeftArm/mixamorig_LeftForeArm/mixamorig_LeftHand/mixamorig_LeftHandPinky1/mixamorig_LeftHandPinky2/mixamorig_LeftHandPinky3/mixamorig_LeftHandPinky4","关节/mixamorig_Hips/mixamorig_Spine/mixamorig_Spine1/mixamorig_Spine2/mixamorig_RightShoulder","关节/mixamorig_Hips/mixamorig_Spine/mixamorig_Spine1/mixamorig_Spine2/mixamorig_RightShoulder/mixamorig_RightArm","关节/mixamorig_Hips/mixamorig_Spine/mixamorig_Spine1/mixamorig_Spine2/mixamorig_RightShoulder/mixamorig_RightArm/mixamorig_RightForeArm","关节/mixamorig_Hips/mixamorig_Spine/mixamorig_Spine1/mixamorig_Spine2/mixamorig_RightShoulder/mixamorig_RightArm/mixamorig_RightForeArm/mixamorig_RightHand","关节/mixamorig_Hips/mixamorig_Spine/mixamorig_Spine1/mixamorig_Spine2/mixamorig_RightShoulder/mixamorig_RightArm/mixamorig_RightForeArm/mixamorig_RightHand/mixamorig_RightHandThumb1","关节/mixamorig_Hips/mixamorig_Spine/mixamorig_Spine1/mixamorig_Spine2/mixamorig_RightShoulder/mixamorig_RightArm/mixamorig_RightForeArm/mixamorig_RightHand/mixamorig_RightHandThumb1/mixamorig_RightHandThumb2","关节/mixamorig_Hips/mixamorig_Spine/mixamorig_Spine1/mixamorig_Spine2/mixamorig_RightShoulder/mixamorig_RightArm/mixamorig_RightForeArm/mixamorig_RightHand/mixamorig_RightHandThumb1/mixamorig_RightHandThumb2/mixamorig_RightHandThumb3","关节/mixamorig_Hips/mixamorig_Spine/mixamorig_Spine1/mixamorig_Spine2/mixamorig_RightShoulder/mixamorig_RightArm/mixamorig_RightForeArm/mixamorig_RightHand/mixamorig_RightHandThumb1/mixamorig_RightHandThumb2/mixamorig_RightHandThumb3/mixamorig_RightHandThumb4","关节/mixamorig_Hips/mixamorig_Spine/mixamorig_Spine1/mixamorig_Spine2/mixamorig_RightShoulder/mixamorig_RightArm/mixamorig_RightForeArm/mixamorig_RightHand/mixamorig_RightHandIndex1","关节/mixamorig_Hips/mixamorig_Spine/mixamorig_Spine1/mixamorig_Spine2/mixamorig_RightShoulder/mixamorig_RightArm/mixamorig_RightForeArm/mixamorig_RightHand/mixamorig_RightHandIndex1/mixamorig_RightHandIndex2","关节/mixamorig_Hips/mixamorig_Spine/mixamorig_Spine1/mixamorig_Spine2/mixamorig_RightShoulder/mixamorig_RightArm/mixamorig_RightForeArm/mixamorig_RightHand/mixamorig_RightHandIndex1/mixamorig_RightHandIndex2/mixamorig_RightHandIndex3","关节/mixamorig_Hips/mixamorig_Spine/mixamorig_Spine1/mixamorig_Spine2/mixamorig_RightShoulder/mixamorig_RightArm/mixamorig_RightForeArm/mixamorig_RightHand/mixamorig_RightHandIndex1/mixamorig_RightHandIndex2/mixamorig_RightHandIndex3/mixamorig_RightHandIndex4","关节/mixamorig_Hips/mixamorig_Spine/mixamorig_Spine1/mixamorig_Spine2/mixamorig_RightShoulder/mixamorig_RightArm/mixamorig_RightForeArm/mixamorig_RightHand/mixamorig_RightHandMiddle1","关节/mixamorig_Hips/mixamorig_Spine/mixamorig_Spine1/mixamorig_Spine2/mixamorig_RightShoulder/mixamorig_RightArm/mixamorig_RightForeArm/mixamorig_RightHand/mixamorig_RightHandMiddle1/mixamorig_RightHandMiddle2","关节/mixamorig_Hips/mixamorig_Spine/mixamorig_Spine1/mixamorig_Spine2/mixamorig_RightShoulder/mixamorig_RightArm/mixamorig_RightForeArm/mixamorig_RightHand/mixamorig_RightHandMiddle1/mixamorig_RightHandMiddle2/mixamorig_RightHandMiddle3","关节/mixamorig_Hips/mixamorig_Spine/mixamorig_Spine1/mixamorig_Spine2/mixamorig_RightShoulder/mixamorig_RightArm/mixamorig_RightForeArm/mixamorig_RightHand/mixamorig_RightHandMiddle1/mixamorig_RightHandMiddle2/mixamorig_RightHandMiddle3/mixamorig_RightHandMiddle4","关节/mixamorig_Hips/mixamorig_Spine/mixamorig_Spine1/mixamorig_Spine2/mixamorig_RightShoulder/mixamorig_RightArm/mixamorig_RightForeArm/mixamorig_RightHand/mixamorig_RightHandRing1","关节/mixamorig_Hips/mixamorig_Spine/mixamorig_Spine1/mixamorig_Spine2/mixamorig_RightShoulder/mixamorig_RightArm/mixamorig_RightForeArm/mixamorig_RightHand/mixamorig_RightHandRing1/mixamorig_RightHandRing2","关节/mixamorig_Hips/mixamorig_Spine/mixamorig_Spine1/mixamorig_Spine2/mixamorig_RightShoulder/mixamorig_RightArm/mixamorig_RightForeArm/mixamorig_RightHand/mixamorig_RightHandRing1/mixamorig_RightHandRing2/mixamorig_RightHandRing3","关节/mixamorig_Hips/mixamorig_Spine/mixamorig_Spine1/mixamorig_Spine2/mixamorig_RightShoulder/mixamorig_RightArm/mixamorig_RightForeArm/mixamorig_RightHand/mixamorig_RightHandRing1/mixamorig_RightHandRing2/mixamorig_RightHandRing3/mixamorig_RightHandRing4","关节/mixamorig_Hips/mixamorig_Spine/mixamorig_Spine1/mixamorig_Spine2/mixamorig_RightShoulder/mixamorig_RightArm/mixamorig_RightForeArm/mixamorig_RightHand/mixamorig_RightHandPinky1","关节/mixamorig_Hips/mixamorig_Spine/mixamorig_Spine1/mixamorig_Spine2/mixamorig_RightShoulder/mixamorig_RightArm/mixamorig_RightForeArm/mixamorig_RightHand/mixamorig_RightHandPinky1/mixamorig_RightHandPinky2","关节/mixamorig_Hips/mixamorig_Spine/mixamorig_Spine1/mixamorig_Spine2/mixamorig_RightShoulder/mixamorig_RightArm/mixamorig_RightForeArm/mixamorig_RightHand/mixamorig_RightHandPinky1/mixamorig_RightHandPinky2/mixamorig_RightHandPinky3","关节/mixamorig_Hips/mixamorig_Spine/mixamorig_Spine1/mixamorig_Spine2/mixamorig_RightShoulder/mixamorig_RightArm/mixamorig_RightForeArm/mixamorig_RightHand/mixamorig_RightHandPinky1/mixamorig_RightHandPinky2/mixamorig_RightHandPinky3/mixamorig_RightHandPinky4","关节/mixamorig_Hips/mixamorig_RightUpLeg","关节/mixamorig_Hips/mixamorig_RightUpLeg/mixamorig_LeftLeg","关节/mixamorig_Hips/mixamorig_RightUpLeg/mixamorig_LeftLeg/mixamorig_LeftFoot","关节/mixamorig_Hips/mixamorig_RightUpLeg/mixamorig_LeftLeg/mixamorig_LeftFoot/mixamorig_LeftToeBase","关节/mixamorig_Hips/mixamorig_RightUpLeg/mixamorig_LeftLeg/mixamorig_LeftFoot/mixamorig_LeftToeBase/mixamorig_LeftToe_End","关节/mixamorig_Hips/mixamorig_RightUpLeg_2","关节/mixamorig_Hips/mixamorig_RightUpLeg_2/mixamorig_RightLeg","关节/mixamorig_Hips/mixamorig_RightUpLeg_2/mixamorig_RightLeg/mixamorig_RightFoot","关节/mixamorig_Hips/mixamorig_RightUpLeg_2/mixamorig_RightLeg/mixamorig_RightFoot/mixamorig_RightToeBase","关节/mixamorig_Hips/mixamorig_RightUpLeg_2/mixamorig_RightLeg/mixamorig_RightFoot/mixamorig_RightToeBase/mixamorig_LeftToe_End_2"],[[[7,1,-1.7305636108285946e-29,9.742207041085749e-15,0,0,1,1.7763568394002505e-15,0,-9.742207041085749e-15,-1.7763568394002505e-15,1,0,-3.814697180359872e-8,-0.7171837687492371,-0.001184552675113082,1],[7,1,3.2279146591839226e-19,-2.7753697915638418e-17,0,1.735489176661365e-29,0.9999323487281799,0.01162978820502758,0,2.7755575615628914e-17,-0.01162978820502758,0.9999323487281799,0,-3.814697180359872e-8,-0.834068775177002,-0.010242451913654804,1],[7,1,3.227948521890249e-19,8.604246969690684e-16,0,-1.0329326909388552e-17,0.9999323487281799,0.011629783548414707,0,-8.603627576848005e-16,-0.011629783548414707,0.9999323487281799,0,-3.814697180359872e-8,-0.8925536870956421,-0.01017263438552618,1],[7,1,3.227948521890249e-19,-2.7753697915638418e-17,0,-3.519690677538987e-24,0.9999323487281799,0.011629783548414707,0,2.7755575615628914e-17,-0.011629783548414707,0.9999323487281799,0,-3.814697180359872e-8,-0.9662537574768066,-0.01017263438552618,1],[7,1,1.1775428739323234e-15,1.0121773346772125e-13,0,-1.1775428739323234e-15,1,1.64625257870199e-15,0,-1.0121773346772125e-13,-1.64625257870199e-15,1,0,-3.814697180359872e-8,-1.0492136478424072,0.002029630122706294,1],[7,1,1.1775428739323234e-15,-5.363673508161984e-15,0,-1.1775428739323234e-15,1,-1.3183898417423734e-16,0,5.363673508161984e-15,1.3183898417423734e-16,1,0,-3.814697180359872e-8,-1.0931763648986816,0.0015630271518602967,1],[7,1,1.1775428739323234e-15,-5.363673508161984e-15,0,-1.1775428739323234e-15,1,-1.3357370765021415e-16,0,5.363673508161984e-15,1.3357370765021415e-16,1,0,-3.814697180359872e-8,-1.741969347000122,-0.00048589680227451026,1],[7,-0.0046868836507201195,0.9649047255516052,-0.26255837082862854,0,-0.011739431880414486,-0.2625962495803833,-0.9648343920707703,0,-0.999920129776001,-0.0014397803461179137,0.012558192014694214,0,0.010587646625936031,0.2031676471233368,1.0321258306503296,1],[7,0.003944264724850655,0.7534661293029785,-0.657474935054779,0,-0.014087856747210026,-0.6573728919029236,-0.7534337043762207,0,-0.9998930096626282,0.012234154157340527,0.008021869696676731,0,0.01107680145651102,0.5364810228347778,0.8352064490318298,1],[7,0.007419626694172621,0.749530553817749,-0.6619281768798828,0,-0.0171198770403862,-0.6617541909217834,-0.7495254278182983,0,-0.9998258948326111,0.016893329098820686,0.00792190246284008,0,0.013255110941827297,0.39772388339042664,0.8379159569740295,1],[7,-0.08336720615625381,0.7528182864189148,-0.6529276371002197,0,-0.018649129197001457,-0.6562723517417908,-0.7542935609817505,0,-0.9963443875312805,-0.05070681497454643,0.06875099986791611,0,0.049109652638435364,0.225385844707489,0.8396355509757996,1],[7,0.48557817935943604,0.3587550222873688,-0.7971879839897156,0,-0.48652297258377075,-0.6467328667640686,-0.5873942375183105,0,-0.7262983322143555,0.6730760931968689,-0.1394968330860138,0,0.193938210606575,0.3347976505756378,0.7591465711593628,1],[7,0.48557817935943604,0.31278055906295776,-0.8163223266601562,0,-0.48652297258377075,-0.6791301965713501,-0.5496158003807068,0,-0.7262983322143555,0.6640410423278809,-0.17759589850902557,0,0.19570371508598328,0.3521764278411865,0.7440324425697327,1],[7,0.48557817935943604,0.3590691387653351,-0.7970465421676636,0,-0.48652297258377075,-0.646501362323761,-0.5876490473747253,0,-0.7262983322143555,0.673130989074707,-0.1392315924167633,0,0.19914838671684265,0.26714378595352173,0.7713074088096619,1],[7,0.48557817935943604,0.3590691089630127,-0.7970465421676636,0,-0.48652297258377075,-0.646501362323761,-0.5876490473747253,0,-0.7262983322143555,0.673130989074707,-0.1392315924167633,0,0.20092590153217316,0.23926964402198792,0.7765176296234131,1],[7,-0.06079445034265518,0.7605703473091125,-0.6464029550552368,0,-0.038286082446575165,-0.648901104927063,-0.75990891456604,0,-0.9974157810211182,-0.02145000547170639,0.06856884807348251,0,0.07827360183000565,0.1613060086965561,0.8550983667373657,1],[7,-0.15285855531692505,0.700215756893158,-0.6973751783370972,0,-0.12897947430610657,-0.7137677073478699,-0.6884039044380188,0,-0.9797951579093933,-0.015281354077160358,0.19941896200180054,0,0.20504333078861237,0.18591083586215973,0.840356171131134,1],[7,-0.12798742949962616,0.8155727386474609,-0.5643228888511658,0,-0.1536901444196701,-0.5784387588500977,-0.8011166453361511,0,-0.9797951579093933,-0.015801984816789627,0.1993783861398697,0,0.22278936207294464,0.0056490288116037846,0.875379204750061,1],[7,-0.12798742949962616,0.8155727386474609,-0.5643228888511658,0,-0.1536901444196701,-0.5784388184547424,-0.8011166453361511,0,-0.9797951579093933,-0.015801982954144478,0.1993783861398697,0,0.23000018298625946,-0.007563584018498659,0.8854246139526367,1],[7,-0.012685715220868587,0.7501528263092041,-0.6611427664756775,0,-0.07986673712730408,-0.6598436236381531,-0.7471463680267334,0,-0.9967248439788818,0.043325234204530716,0.068282850086689,0,0.06569062918424606,0.17506955564022064,0.8562135696411133,1],[7,-0.012685715220868587,0.7448733448982239,-0.6670852899551392,0,-0.07986673712730408,-0.6657623052597046,-0.7418772578239441,0,-0.9967248439788818,0.043866682797670364,0.06793627887964249,0,0.0645260289311409,0.1270984262228012,0.8877372145652771,1],[7,-0.012685715220868587,0.7401406764984131,-0.6723324060440063,0,-0.07986673712730408,-0.6709882616996765,-0.7371540069580078,0,-0.9967248439788818,0.0443456694483757,0.06762459129095078,0,0.06714467704296112,0.10990922898054123,0.9033576846122742,1],[7,-0.012685715220868587,0.7401406764984131,-0.6723323464393616,0,-0.07986673712730408,-0.6709882616996765,-0.7371540665626526,0,-0.9967248439788818,0.0443456694483757,0.06762459129095078,0,0.07063557952642441,0.08992308378219604,0.9251139760017395,1],[7,-0.039409078657627106,0.9639158248901367,-0.2632739543914795,0,-0.056814972311258316,-0.2652139663696289,-0.9625142216682434,0,-0.997606635093689,-0.02297389507293701,0.06521669030189514,0,0.02184578776359558,-0.23950058221817017,0.8483595848083496,1],[7,-0.039409078657627106,0.9607017636299133,-0.27477097511291504,0,-0.056814972311258316,-0.27669408917427063,-0.9592770338058472,0,-0.997606635093689,-0.022193117067217827,0.06548650562763214,0,0.022224562242627144,-0.27036237716674805,0.84995037317276,1],[7,0.11289023607969284,0.9243649840354919,-0.3644244372844696,0,-0.11579107493162155,-0.35203105211257935,-0.9287984371185303,0,-0.9868375062942505,0.14704936742782593,0.06729234755039215,0,-0.009692421182990074,-0.21193096041679382,0.8790941834449768,1],[7,0.11289023607969284,0.9243649840354919,-0.3644244372844696,0,-0.11579107493162155,-0.35203105211257935,-0.9287984371185303,0,-0.9868375062942505,0.14704936742782593,0.06729234755039215,0,-0.012096988968551159,-0.23888927698135376,0.8900634050369263,1],[7,-0.0072664231993258,0.9804823994636536,-0.1964724212884903,0,-0.08452767133712769,-0.19637666642665863,-0.9768783450126648,0,-0.9963946342468262,0.009508945047855377,0.08430485427379608,0,-0.008204436860978603,-0.29533669352531433,0.8326663970947266,1],[7,-0.0072664231993258,0.9622856378555298,-0.2719440758228302,0,-0.08452767133712769,-0.27156901359558105,-0.9586998224258423,0,-0.9963946342468262,0.016020480543375015,0.08331310003995895,0,-0.008202089928090572,-0.2664358913898468,0.8532657623291016,1],[7,-0.0072664231993258,0.9614323973655701,-0.2749454379081726,0,-0.08452767133712769,-0.2745591700077057,-0.9578477740287781,0,-0.9963946342468262,0.016280369833111763,0.08326270431280136,0,-0.011193903163075447,-0.2846507728099823,0.8551548719406128,1],[7,-0.0072664231993258,0.9614323973655701,-0.2749454081058502,0,-0.08452767133712769,-0.2745591402053833,-0.9578477740287781,0,-0.9963946342468262,0.016280367970466614,0.08326270431280136,0,-0.01119487639516592,-0.307998389005661,0.864650547504425,1],[7,-0.0046868836507201195,0.9649047255516052,0.26255837082862854,0,-0.014289864338934422,0.2624698281288147,-0.9648343920707703,0,-0.9998869299888611,-0.008273989893496037,0.012558192014694214,0,0.012560814619064331,-0.20305520296096802,1.0321258306503296,1],[7,0.003944264724850655,0.7534661293029785,0.657474935054779,0,-0.007204806432127953,0.6574843525886536,-0.7534337043762207,0,-0.9999662637710571,-0.001765237539075315,0.008021869696676731,0,0.005459578242152929,-0.5365675687789917,0.8352064490318298,1],[7,0.007419626694172621,0.749530553817749,0.6619281768798828,0,-0.004016355145722628,0.6619634032249451,-0.7495254278182983,0,-0.9999644160270691,0.0029026600532233715,0.00792190246284008,0,0.005379122216254473,-0.3979083299636841,0.8379159569740295,1],[7,-0.08336720615625381,0.7528182864189148,0.6529276371002197,0,-0.161787748336792,0.6362907290458679,-0.7542935609817505,0,-0.9832978248596191,-0.1685190498828888,0.06875099986791611,0,0.09723351150751114,-0.20917977392673492,0.8396355509757996,1],[7,0.48557817935943604,0.3587550222873688,0.7971879839897156,0,0.7611258625984192,0.2750553786754608,-0.5873942375183105,0,-0.43000146746635437,0.8919861912727356,-0.1394968330860138,0,-0.3769994080066681,-0.08702263981103897,0.7591465711593628,1],[7,0.48557817935943604,0.31278055906295776,0.8163223266601562,0,0.8195300102233887,0.16215133666992188,-0.5496158003807068,0,-0.30427688360214233,0.9358820915222168,-0.17759589850902557,0,-0.40158194303512573,-0.032559435814619064,0.7440324425697327,1],[7,0.48557817935943604,0.3590691387653351,0.7970465421676636,0,0.7606741189956665,0.27575990557670593,-0.5876490473747253,0,-0.43080011010169983,0.8916422128677368,-0.1392315924167633,0,-0.3137678802013397,-0.1121409609913826,0.7713074088096619,1],[7,0.48557817935943604,0.3590691387653351,0.7970465421676636,0,0.7606741189956665,0.27575990557670593,-0.5876490473747253,0,-0.43080011010169983,0.8916422128677368,-0.1392315924167633,0,-0.28763771057128906,-0.1220071017742157,0.7765176296234131,1],[7,-0.06079445034265518,0.7605703473091125,0.6464029550552368,0,-0.14087821543216705,0.6345800161361694,-0.75990891456604,0,-0.9881585836410522,-0.13726232945919037,0.06856884807348251,0,0.10290326923131943,-0.14682406187057495,0.8550983667373657,1],[7,-0.15285855531692505,0.700215756893158,0.6973751783370972,0,-0.41470375657081604,0.595080554485321,-0.6884039044380188,0,-0.8970256447792053,-0.39443254470825195,0.19941896200180054,0,0.26386651396751404,-0.08354684710502625,0.840356171131134,1],[7,-0.12798742949962616,0.8155727386474609,0.5643228888511658,0,-0.32348698377609253,0.5035555958747864,-0.8011166453361511,0,-0.937536895275116,-0.28508397936820984,0.1993783861398697,0,0.2138102799654007,0.06286633759737015,0.875379204750061,1],[7,-0.12798742949962616,0.8155727386474609,0.5643228888511658,0,-0.32348698377609253,0.5035555958747864,-0.8011166453361511,0,-0.937536895275116,-0.28508397936820984,0.1993783861398697,0,0.21662725508213043,0.07765260338783264,0.8854246139526367,1],[7,-0.012685715220868587,0.7501528263092041,0.6611427664756775,0,-0.10213171690702438,0.656765878200531,-0.7471463680267334,0,-0.9946900010108948,-0.07700173556804657,0.068282850086689,0,0.07157251983880997,-0.17274832725524902,0.8562135696411133,1],[7,-0.012685715220868587,0.7448733448982239,0.6670852899551392,0,-0.10249064117670059,0.6626566052436829,-0.7418772578239441,0,-0.994653046131134,-0.07778124511241913,0.06793627887964249,0,0.06881650537252426,-0.12482751160860062,0.8877372145652771,1],[7,-0.012685715220868587,0.7401406764984131,0.6723324060440063,0,-0.10281401127576828,0.6678571701049805,-0.7371540069580078,0,-0.9946197271347046,-0.07847651839256287,0.06762459129095078,0,0.0708717331290245,-0.10754368454217911,0.9033576846122742,1],[7,-0.012685716152191162,0.7401406764984131,0.6723323464393616,0,-0.10281401127576828,0.6678571701049805,-0.7371540665626526,0,-0.9946197271347046,-0.07847651839256287,0.06762459129095078,0,0.07367567718029022,-0.08744964003562927,0.9251139760017395,1],[7,-0.039409078657627106,0.9639158248901367,0.2632739543914795,0,-0.07827536761760712,0.25969088077545166,-0.9625142216682434,0,-0.9961525201797485,-0.05853966251015663,0.06521669030189514,0,0.002221903298050165,0.2404845803976059,0.8483595848083496,1],[7,-0.039409078657627106,0.9607017636299133,0.27477097511291504,0,-0.07928656041622162,0.27111107110977173,-0.9592770338058472,0,-0.9960725903511047,-0.059589870274066925,0.06548650562763214,0,0.000006010661309119314,0.27127429842948914,0.84995037317276,1],[7,0.11289023607969284,0.9243649840354919,0.3644244372844696,0,-0.027666166424751282,0.3695510923862457,-0.9287984371185303,0,-0.9932222366333008,0.09477005153894424,0.06729234755039215,0,0.041596848517656326,0.20803454518318176,0.8790941834449768,1],[7,0.11289023607969284,0.9243649840354919,0.3644244372844696,0,-0.027666166424751282,0.3695510923862457,-0.9287984371185303,0,-0.9932222366333008,0.09477005153894424,0.06729234755039215,0,0.04575088247656822,0.2347792088985443,0.8900634050369263,1],[7,-0.0072664231993258,0.9804823994636536,0.1964724212884903,0,-0.08742894977331161,0.1951022744178772,-0.9768783450126648,0,-0.9961442351341248,-0.02427578903734684,0.08430485427379608,0,-0.012580816633999348,0.29518264532089233,0.8326663970947266,1],[7,-0.0072664231993258,0.9622856378555298,0.2719440758228302,0,-0.08861915022134781,0.2702615261077881,-0.9586998224258423,0,-0.996039092540741,-0.031065771356225014,0.08331310003995895,0,-0.012224752455949783,0.2662816345691681,0.8532657623291016,1],[7,-0.0072664231993258,0.9614323973655701,0.2749454379081726,0,-0.08866796642541885,0.27325019240379333,-0.9578477740287781,0,-0.9960347414016724,-0.03133897855877876,0.08326270431280136,0,-0.015495111234486103,0.2844490706920624,0.8551548719406128,1],[7,-0.0072664231993258,0.9614323973655701,0.2749454081058502,0,-0.08866796642541885,0.27325016260147095,-0.9578477740287781,0,-0.9960347414016724,-0.03133897855877876,0.08326270431280136,0,-0.015848981216549873,0.3077940046787262,0.864650547504425,1],[7,-0.9997187852859497,-0.023712676018476486,-9.506909148804255e-12,0,0.023703360930085182,-0.9993261098861694,-0.028027119114995003,0,0.0006645979592576623,-0.028019238263368607,0.9996071457862854,0,0.0854240357875824,0.6503899693489075,0.01403839886188507,1],[7,-0.999999463558197,0.0010636295191943645,-0.00001868096114776563,0,-0.0010611009784042835,-0.9985631108283997,-0.0535774752497673,0,-0.000075640702561941,-0.05357742682099342,0.9985637068748474,0,0.12161237746477127,0.3477100431919098,0.00549126323312521,1],[7,-0.9978870749473572,-0.0522007942199707,-0.03868475556373596,0,-0.03225036337971687,-0.11892067641019821,0.9923798441886902,0,-0.05640343576669693,0.9915305972099304,0.11698590219020844,0,0.1183723732829094,0.06474423408508301,-0.009296146221458912,1],[7,-0.9985212087631226,-0.033698052167892456,0.04265885800123215,0,0.02130742371082306,0.4793204963207245,0.8773812651634216,0,-0.05001330375671387,0.8769927620887756,-0.4778936803340912,0,0.11769890040159225,-0.047315631061792374,0.014486984349787235,1],[7,-0.9985212087631226,-0.033698052167892456,0.04265885800123215,0,0.02130742371082306,0.4793204963207245,0.8773812651634216,0,-0.05001330375671387,0.8769927620887756,-0.4778936803340912,0,0.11769890040159225,-0.08633074164390564,0.014486984349787235,1],[7,-0.9997187852859497,-0.023712676018476486,-9.506910016165993e-12,0,0.023703360930085182,-0.9993261098861694,-0.028027119114995003,0,0.0006645979592576623,-0.028019238263368607,0.9996071457862854,0,-0.11616426706314087,0.6456084251403809,0.01403839886188507,1],[7,-0.999999463558197,0.001063630566932261,-0.00001872065695351921,0,-0.001061102608218789,-0.998565137386322,-0.05354016646742821,0,-0.0000756407534936443,-0.05354011803865433,0.998565673828125,0,-0.12087263911962509,0.3479681611061096,0.005473732948303223,1],[7,-0.9978870749473572,-0.0522007942199707,0.03868475556373596,0,0.04448218271136284,-0.1149066910147667,0.9923798441886902,0,-0.04735787957906723,0.9920037984848022,0.11698590219020844,0,-0.12448152899742126,0.0520402230322361,-0.009296146221458912,1],[7,-0.9985212087631226,-0.03369805961847305,-0.04265885800123215,0,-0.05357431620359421,0.4767933785915375,0.8773812651634216,0,-0.009226583875715733,0.8783692121505737,-0.4778936803340912,0,-0.11424112319946289,-0.05514313653111458,0.014486984349787235,1],[7,-0.9985212087631226,-0.03369805961847305,-0.04265885800123215,0,-0.05357431620359421,0.4767933785915375,0.8773812651634216,0,-0.009226583875715733,0.8783692121505737,-0.4778936803340912,0,-0.11161075532436371,-0.0940694734454155,0.014486984349787235,1]],8,8,8,8,8,8,8,8,8,8,8,8,8,8,8,8,8,8,8,8,8,8,8,8,8,8,8,8,8,8,8,8,8,8,8,8,8,8,8,8,8,8,8,8,8,8,8,8,8,8,8,8,8,8,8,8,8,8,8,8,8,8,8,8,8]]],0,0,[],[],[]],[[[17,"Material__106",[{"rasterizerState":{},"blendState":{"targets":[{}]},"depthStencilState":{}}],[{"USE_ALBEDO_MAP":true,"DCC_APP_NAME":0}],[[[{"albedoScale":1,"specularFactor":1,"shininessExponent":32,"emissiveScale":1},"mainColor",8,[4,4294967295],"specularColor",8,[4,4286348412],"emissive",8,[4,4278190080],"mainTexture",6,0]],11]]],0,0,[0,0],[6,7],[69,10]],[[[19,"苏尔"],[26,"苏尔",[-3,-4],[[49,-2,[8,"40HcGhz9pRqpl99HSp8+c1"]]],[1,"45UDS+VRRYaKfpI+U/RcFZ",null,null,null,-1,0]],[30,"mixamorig_LeftHand",[-5,-6,-7,-8,-9],[1,"6781E1Zo1TyZH6GwO88d9h",null,null,null,1,0],[1,0.00007116323104128242,0.16697032749652863,-0.0015942315803840756],[3,-0.004442056584472314,-0.030516376330659917,-0.03365899579620523,0.9989575020544852],[1,-0.6276161314154564,-3.5205218444943416,-3.840357225047876]],[30,"mixamorig_RightHand",[-10,-11,-12,-13,-14],[1,"a6UgtimxFXR6/c6xSbjgmS",null,null,null,1,0],[1,-0.0032342160120606422,-0.16693900525569916,-0.0015942315803840756],[3,0.007478148793603064,-0.029917527458844687,-0.08635914460998993,0.9957866824694941],[1,0.5657411281373567,-3.392620280140758,-9.929601493616143]],[22,"mixamorig_Hips",[-15,-16,-17],[1,"7c/+w66LBTMYCFSqu80AMl",null,null,null,1,0],[1,3.814697180359872e-8,0.7171837687492371,0.001184552675113082]],[22,"mixamorig_Spine2",[-18,-19,-20],[1,"5731glKUlXV44AuisH7/mr",null,null,null,1,0],[1,-3.462567787107378e-17,0.07370004802942276,-2.992533998380509e-11]],[20,"关节",1,[4],[1,"34XuBURsVRfKVYrCe0nmXr",null,null,null,1,0]],[7,"mixamorig_Spine",4,[-21],[1,"c8sLqvXN9VeaSxG14oXW5U",null,null,null,1,0],[1,2.86539396693855e-18,0.1169477179646492,-0.0006428364431485534],[3,-0.0058149924762980355,-4.884898822816793e-15,-2.840612728016906e-17,0.9999830927883234],[1,-0.6663528089779736,-5.597776360687116e-13,3.312148187911076e-22]],[21,"mixamorig_Spine1",7,[5],[1,"8652/1fC9cYbV/391aB17r",null,null,null,1,0],[1,-2.191944250843043e-17,0.058484919369220734,-0.00006981345359236002]],[7,"mixamorig_Neck",5,[-22],[1,"c56OPjK2BZQIeN66k7O6HG",null,null,null,1,0],[1,-5.845369736790496e-17,0.08291251212358475,-8.247900973312738e-11],[3,0.00581499014807028,5.062531376446305e-14,-2.943907008429333e-16,0.9999830928018622],[1,0.6663525421782143,5.801331714738488e-12,-2.605549046225628e-21]],[42,"mixamorig_Head",9,[[11,"mixamorig_HeadTop_End",-23,[1,"b1v7ZaLb5SKYfKHqztKfBm",null,null,null,1,0],[1,-5.174973731634158e-16,0.6487929224967957,0.0020489240996539593]]],[1,"4fjKJDWTJVipBd8j1oBG3l",null,null,null,1,0],[1,-1.2052230636156467e-16,0.0439627543091774,0.0004666027962230146]],[7,"mixamorig_LeftShoulder",5,[-24],[1,"1eWVqb1OlakJ8nuVhYgXVE",null,null,null,1,0],[1,0.07500545680522919,0.0830054059624672,-0.00005161075387150049],[3,-0.5604770835614566,-0.4303453905668743,0.5631574448591443,-0.4283946497331728],[1,105.22212115356227,90.26854205003302,-0.006291867975238871]],[7,"mixamorig_LeftArm",11,[-25],[1,"b5dKUiiSdWP7kuW+prJgzN",null,null,null,1,0],[1,0.0005669468664564192,0.08505517244338989,0.04650251194834709],[3,0.22397873367946794,0.0010017516575809955,0.004358857048218733,0.9745837694719689],[1,25.88592600950146,-4.302280448484193e-8,0.512510981884216]],[7,"mixamorig_LeftForeArm",12,[2],[1,"c2eGO22HZb45TXSJSp7sRp",null,null,null,1,0],[1,-0.0003665787517093122,0.14367254078388214,-0.0050516799092292786],[3,0.002962954295845446,0.00000683260385089823,0.0023062745678426766,0.9999929509515425],[1,0.3395309520772798,-9.51636465564337e-8,0.2642809923548067]],[7,"mixamorig_LeftHandThumb1",2,[-26],[1,"26yPMLmOFY94YSm15yuie/",null,null,null,1,0],[1,-0.01892518810927868,0.02191099338233471,0.01503001432865858],[3,0.13952709796228122,0.05950284403090734,0.38773939185187906,0.9092028181284926],[1,17.449197703557875,2.2659050836400413e-7,46.19269808739389]],[7,"mixamorig_LeftHandThumb2",14,[-27],[1,"5c4UB6+yBds5fX1hYRlgMk",null,null,null,1,0],[1,-0.001765502616763115,0.025558320805430412,-0.0037318619433790445],[3,0.028481881442510213,3.321085738226076e-13,-9.629517567143012e-15,0.999594308922122],[1,3.2642246327054165,3.8072828577801925e-11,-1.908338291297177e-14]],[12,"mixamorig_LeftHandThumb3",15,[[11,"mixamorig_LeftHandThumb4",-28,[1,"64uzMYqz9XPbBPdC3fkMyw",null,null,null,1,0],[1,-0.0017775088781490922,0.027874141931533813,-0.005210230592638254]]],[1,"36VJpm4rBaBYc4qr8bIqnb",null,null,null,1,0],[1,-0.0034446849022060633,0.04124988615512848,-0.010689782910048962],[3,-0.028678827260135847,-3.333706226874799e-13,-9.675681165308342e-15,0.9995886778405321],[1,-3.286802183996949,-3.8217543970081875e-11,-1.272228050404609e-14]],[7,"mixamorig_LeftHandIndex1",2,[-29],[1,"c1+ncWyq5ZWpcRO5cDaiAH",null,null,null,1,0],[1,-0.02408001571893692,0.05445576086640358,-0.014042273163795471],[3,-0.004304637146256776,-0.00006443915399069292,0.014968888643302057,0.9998786918018698],[1,-0.493331886723004,4.926320557246794e-7,1.715388246184382]],[7,"mixamorig_LeftHandIndex2",17,[-30],[1,"8epT7JSOlQgoTQs7aCDPeX",null,null,null,1,0],[1,-0.015652650967240334,0.05242609605193138,-0.017900560051202774],[3,0.04431380336393524,-0.06514988101738768,-0.0028960548838810056,0.9968868505005732],[1,5.047420497805173,-7.449141932013117,-0.6616753129167409]],[12,"mixamorig_LeftHandIndex3",18,[[11,"mixamorig_LeftHandIndex4",-31,[1,"fctRgLVa5cB6KSinE8j5k2",null,null,null,1,0],[1,-0.00721082603558898,0.013212619349360466,-0.010045420378446579]]],[1,"98P5co2upWv7nJKHNHWcID",null,null,null,1,0],[1,-0.012370898388326168,0.020561333745718002,-0.02065853215754032],[3,-0.08717746969755158,-0.0013621970912897,0.017476906873872485,0.9960385489138153],[1,-10.004375672603949,0.019124674771747438,2.0087919744274947]],[7,"mixamorig_LeftHandMiddle1",2,[-32],[1,"38v9kZ6UJaC7Sk97vumpmt",null,null,null,1,0],[1,-0.0008140283753164113,0.054247207939624786,-0.018435223028063774],[3,0.005443602008230806,0.00025478969397484965,0.04675295323463935,0.9988916175658034],[1,0.6244768096676696,3.2450209328470953e-7,5.359527135340801]],[7,"mixamorig_LeftHandMiddle2",20,[-33],[1,"e2uSeDQE1QLrrWQOgIx//n",null,null,null,1,0],[1,0.0011645978083834052,0.05503226816654205,-0.03250598907470703],[3,0.003974810353264317,1.247474160530712e-16,-3.866007040490275e-17,0.9999921004101259],[1,0.4554809145853367,1.4312496843220922e-14,-4.373262826108333e-15]],[12,"mixamorig_LeftHandMiddle3",21,[[11,"mixamorig_LeftHandMiddle4",-34,[1,"c6hLkBZ9BR3pM5ZXKFvEXY",null,null,null,1,0],[1,-0.0034909010864794254,0.019986119121313095,-0.021756300702691078]]],[1,"a2KdJp+4Jf8ZzENi/8Tw2y",null,null,null,1,0],[1,-0.002618648111820221,0.023575665429234505,-0.016374601051211357],[3,0.0035333543190312735,5.831331715831624e-16,7.426788310353785e-17,0.9999937576841449],[1,0.40489342250085364,6.679165161188558e-14,8.74652567968137e-15]],[7,"mixamorig_LeftHandRing1",2,[-35],[1,"bf7dRWY6xXWpQFEwqun0Km",null,null,null,1,0],[1,0.03599829971790314,0.0749371126294136,-0.02912505716085434],[3,-0.2208126229842056,-0.006431501482586223,0.028394917572907078,0.9748816081840618],[1,-25.524535954883667,4.270403116189891e-7,3.3367109289658967]],[7,"mixamorig_LeftHandRing2",23,[-36],[1,"dc+UBE+KNWybbDEL1xRFCj",null,null,null,1,0],[1,-0.00037877418799325824,0.040996748954057693,0.0016998652135953307],[3,0.005973554562230006,8.530438465232879e-16,-7.622072806920905e-17,0.9999821581637804],[1,0.6845230012677296,9.780205475354714e-14,-8.150171563217684e-15]],[12,"mixamorig_LeftHandRing3",24,[[11,"mixamorig_LeftHandRing4",-37,[1,"9ezqyaF8JQkra3GPMAl3A0",null,null,null,1,0],[1,0.002404568251222372,0.026958318427205086,-0.010969219729304314]]],[1,"84z5BZ5PtQ0rgjf4ADmQ81",null,null,null,1,0],[1,-0.002784116193652153,0.02253151871263981,-0.005270681343972683],[3,0.04719606717023057,-0.0038753877750902165,0.08174527315350591,0.9955276103304792],[1,5.501753704779802,-0.8961324317221324,9.345853629798963]],[7,"mixamorig_LeftHandPinky1",2,[-38],[1,"96vUkUanFe0ZVfq5lLjGxl",null,null,null,1,0],[1,0.07254840433597565,0.07502222061157227,-0.030689535662531853],[3,-0.2537141480178196,-0.012784927342975105,0.048676219564231446,0.965969100115196],[1,-29.432950212646645,9.386019055637398e-8,5.7695114782693055]],[7,"mixamorig_LeftHandPinky2",26,[-39],[1,"f7sYYkCvVd4Z2ppRCUstMA",null,null,null,1,0],[1,-0.0000023476084152207477,0.0364907942712307,0.00264161080121994],[3,0.03881820253479958,5.415979433980551e-16,-1.7988663518794336e-16,0.999246289536252],[1,4.449356245354491,6.281595413273709e-14,-1.8188796630559526e-14]],[12,"mixamorig_LeftHandPinky3",27,[[11,"mixamorig_LeftHandPinky4",-40,[1,"50xPFKdF5brrlOkDniGuOS",null,null,null,1,0],[1,9.72934003584669e-7,0.023347578942775726,-0.009495680220425129]]],[1,"5diQSjhwBeSq/ciFFhNBMB",null,null,null,1,0],[1,0.0029918134678155184,0.02088191919028759,-0.000996714225038886],[3,0.0015601873939099322,-4.2318810543139216e-16,5.443674482501639e-17,0.9999987829069072],[1,0.17878437837352454,-4.8503458176897474e-14,6.162324473922048e-15]],[7,"mixamorig_RightShoulder",5,[-41],[1,"e8YOYXZbRR9p10h3NidosI",null,null,null,1,0],[1,-0.07500553876161575,0.0830054059624672,-0.00005161075387150049],[3,0.4276179054994093,0.5625607940740392,-0.43112501297906536,0.561069962705976],[1,74.77862168065928,90.26853852541917,-0.15243290553498115]],[7,"mixamorig_RightArm",29,[-42],[1,"a2/7vh5uVQMov6+Q2ivuad",null,null,null,1,0],[1,0.0013931868597865105,-0.08504565060138702,0.04650251194834709],[3,-0.22397832338978513,0.0010862952217842391,0.0054767899575627116,0.9745781320068456],[1,-25.887359092668593,0.26189767717874984,0.5837685098596931]],[7,"mixamorig_RightForeArm",30,[3],[1,"05kHlIkCdRypl5Q/h39M1Q",null,null,null,1,0],[1,-0.001870719250291586,-0.14366082847118378,-0.0050516799092292786],[3,-0.0029625116831654644,0.00005166994294696113,0.002357630486468534,0.9999928311909209],[1,-0.33949611830007836,0.006721337240904029,0.27014607636118243]],[7,"mixamorig_RightHandThumb1",3,[-43],[1,"1c6yimF6ZfGZ1egMuVaVwa",null,null,null,1,0],[1,-0.01367257721722126,-0.025520874187350273,0.01503001432865858],[3,-0.05108397164477141,0.14282445841579208,0.5916100836536204,0.7918264398456193],[1,-40.289137652412826,47.876992962465664,67.26659389158102]],[7,"mixamorig_RightHandThumb2",32,[-44],[1,"76uZzAsOFV7KOxoAqGMVbL",null,null,null,1,0],[1,-0.023911820724606514,0.00919617060571909,-0.0037318619433790445],[3,0.010093217001017918,0.026633523976467833,0.06399283695534379,0.9975438332171535],[1,0.9664735954813801,2.996551522810297,7.366106948704891]],[12,"mixamorig_RightHandThumb3",33,[[11,"mixamorig_RightHandThumb4",-45,[1,"5eAgd/hydWW6n7gpGA/H+v",null,null,null,1,0],[1,-0.02613018825650215,0.009866136126220226,-0.005210230592638254]]],[1,"b8fdF5UhderbgNYDlLODuf",null,null,null,1,0],[1,-0.03613357990980148,0.020193645730614662,-0.010689782910048962],[3,-0.010151789824644902,-0.02682193820724962,-0.06440976453056882,0.9975113568412539],[1,-1.3697709779547165,-3.1684934648038174,-7.351398657669643]],[7,"mixamorig_RightHandIndex1",3,[-46],[1,"60r54IhCZU9Z/AGQwz+ECQ",null,null,null,1,0],[1,-0.011581802740693092,-0.05840495601296425,-0.014042273163795471],[3,0.004239301221779095,0.000749917938059877,0.0155572780377509,0.9998697100364093],[1,0.4846283952071232,0.0784035192956521,1.7831526115136151]],[7,"mixamorig_RightHandIndex2",35,[-47],[1,"2ahppASsRbWpVqCtpD6i7w",null,null,null,1,0],[1,-0.007125993259251118,-0.05424685403704643,-0.017900560051202774],[3,-0.02348094073600118,-0.07521213631403832,-0.13146670233128785,0.9881843381431258],[1,-3.92609979235671,-9.216806777967863,-14.850307990097573]],[12,"mixamorig_RightHandIndex3",36,[[11,"mixamorig_RightHandIndex4",-48,[1,"adZPEMzbxXOq8OrFLqjcHd",null,null,null,1,0],[1,-0.0028169730212539434,-0.01478627696633339,-0.010045420378446579]]],[1,"fbIX/QdktT7JsVEjfKdyHc",null,null,null,1,0],[1,-0.002676632720977068,-0.02384624071419239,-0.02065853215754032],[3,0.0817526655686904,0.03030296051004939,0.04155464109435973,0.9953247932510569],[1,9.25576294512903,3.080277974530784,5.02989000415829]],[7,"mixamorig_RightHandMiddle1",3,[-49],[1,"8bLTScVH9S2ojJJciuc5gI",null,null,null,1,0],[1,0.011074827052652836,-0.05311092734336853,-0.018435223028063774],[3,-0.0054319448432272035,-0.00043782913850124334,0.04659326638283075,0.9988990788906775],[1,-0.6221457406789676,-0.02120615717812792,5.341322766841127]],[7,"mixamorig_RightHandMiddle2",38,[-50],[1,"4fJm8zk/tUzphEInPqgwa0",null,null,null,1,0],[1,0.003024683566763997,-0.0549614243209362,-0.03250598907470703],[3,-0.003972521133798301,-0.00013487233360348145,-0.00011982480893553077,0.9999920932323966],[1,-0.4552204448121422,-0.01550965574378645,-0.013669406996796786]],[12,"mixamorig_RightHandMiddle3",39,[[11,"mixamorig_RightHandMiddle4",-51,[1,"f77eUrgBtSUYrmpmJAdl+q",null,null,null,1,0],[1,-0.0028039435856044292,-0.02009401097893715,-0.021756300702691078]]],[1,"8boJix+hBc0qxflTNwqb3i",null,null,null,1,0],[1,-0.001814342220313847,-0.023651162162423134,-0.016374601051211357],[3,-0.003531292117060676,-0.00012070054923220398,-0.00010886661150511103,0.9999937517581907],[1,-0.40465862005941844,-0.013875231709530473,-0.012426274653721136]],[7,"mixamorig_RightHandRing1",3,[-52],[1,"01+n+DV9dSUbgl2rRPlR0p",null,null,null,1,0],[1,0.05152209848165512,-0.06524509191513062,-0.02912505716085434],[3,0.21926340406235345,0.026891231469973093,0.039304342023116,0.9745027398664139],[1,25.27116876580123,2.0237289697023573,5.071388845466306]],[7,"mixamorig_RightHandRing2",41,[-53],[1,"ceT8MHjMRd14CEgI4MTtgU",null,null,null,1,0],[1,0.002969146938994527,-0.04089084267616272,0.0016998652135953307],[3,-0.005953551095212229,-0.0004884477095645306,-0.00013655014808177055,0.9999821488417925],[1,-0.6822383121781141,-0.05606415448334548,-0.015313983140510811]],[12,"mixamorig_RightHandRing3",42,[[11,"mixamorig_RightHandRing4",-54,[1,"30khOBpTBSHZP/y1Rsu8Mh",null,null,null,1,0],[1,-0.0041540334932506084,-0.0267446618527174,-0.010969219729304314]]],[1,"439dCc41tdZ7ukYiTObc0g",null,null,null,1,0],[1,-0.000929330475628376,-0.022683849558234215,-0.005270681343972683],[3,-0.04735486225410613,-0.00006635968042865218,0.08041743216298128,0.9956357512773434],[1,-5.481159583085829,0.4344220791238773,9.214977478707779]],[7,"mixamorig_RightHandPinky1",3,[-55],[1,"a9avvG48FQAKherRdM8sxU",null,null,null,1,0],[1,0.08720523118972778,-0.05733107775449753,-0.030689535662531853],[3,0.25346005109608466,0.01709721061051351,0.050784677560985536,0.9658605512250392],[1,29.385442052587912,0.41970335817296484,6.129081580714788]],[7,"mixamorig_RightHandPinky2",44,[-56],[1,"deYOm87fVdfoS2DA7Fwg3P",null,null,null,1,0],[1,0.00053849455434829,-0.03648682311177254,0.00264161080121994],[3,-0.03881385846403716,-0.0005807763550289951,-0.00014002970145535228,0.9992462796936707],[1,-4.448866749635405,-0.06712473930987965,-0.013450985013472628]],[12,"mixamorig_RightHandPinky3",45,[[11,"mixamorig_RightHandPinky4",-57,[1,"bcEGw0vwNSIJUWhNGD6rJy",null,null,null,1,0],[1,0.0003538706514518708,-0.023344896733760834,-0.009495680220425129]]],[1,"1afedF+JtfwZ3XzH9+pWVh",null,null,null,1,0],[1,0.003306821919977665,-0.020834356546401978,-0.000996714225038886],[3,-0.0015600092784370644,-0.0000235717228419883,-0.000006701140878825581,0.9999987828845193],[1,-0.17876398588184234,-0.0027023151051089956,-0.0007636794729708694]],[7,"mixamorig_RightUpLeg",4,[-58],[1,"bbuZ360O1U1Jf6I8xwdRD6",null,null,null,1,0],[1,0.10082246363162994,-0.06886350363492966,0.002949221059679985],[3,0.00016617748711352602,-0.014013950663578542,0.9998314941447339,0.01185600641660831],[1,178.39350258060213,-179.96191063793293,1.3582296731380805]],[7,"mixamorig_LeftLeg",47,[-59],[1,"acZ7YcOzNesIYFnIWi/Frb",null,null,null,1,0],[1,-0.02753562293946743,0.29974696040153503,0.017445292323827744],[3,-0.012785114456120353,-0.00013546540982165963,0.012387815036395229,0.9998415197100441],[1,-1.4652511349812871,0.002629043679579768,1.4196577931526528]],[7,"mixamorig_LeftFoot",48,[-60],[1,"3cSGOxXAhb5oJqYy1S3SKK",null,null,null,1,0],[1,0.00045236072037369013,0.33014988899230957,-0.05197302624583244],[3,0.6835029029093127,0.03160796270027882,-0.006200784730136823,0.7292367713419359],[1,86.23818108469467,3.130351567454965,1.9578677067799812]],[12,"mixamorig_LeftToeBase",49,[[11,"mixamorig_LeftToe_End",-61,[1,"1dmbmiJmVc3r1IndU7SX8Z",null,null,null,1,0],[1,3.1291202962080433e-10,0.039015110582113266,-4.001492279886998e-12]]],[1,"d712wa9pRRyI/IqzBSRnWj",null,null,null,1,0],[1,2.227558137946062e-9,0.11168286204338074,-3.4299119100467124e-9],[3,0.3045831690003741,-0.025688242751792597,0.008217801526927516,0.9521038152870088],[1,35.47951141184015,-3.0909881443964844,-7.100474341251058e-7]],[7,"mixamorig_RightUpLeg_2",4,[-62],[1,"08o4/HRNhYjZhjJkl8mypi",null,null,null,1,0],[1,-0.10082253813743591,-0.06886350363492966,0.002949221059679985],[3,0.00016617748711352602,-0.014013950663578542,0.9998314941447339,0.01185600641660831],[1,178.39350258060213,-179.96191063793293,1.3582296731380805]],[7,"mixamorig_RightLeg",51,[-63],[1,"8diRj6LqtdCak7THtZaaP0",null,null,null,1,0],[1,0.013293048366904259,0.3007153868675232,0.017445292323827744],[3,-0.012766435853444403,-0.00013523400529592765,0.012387818764634037,0.9998417583666018],[1,-1.4631103857885637,0.002629043232626154,1.4196579306550596]],[7,"mixamorig_RightFoot",52,[-64],[1,"cbklt51iNaf5z5l75BvU4H",null,null,null,1,0],[1,0.0002518970868550241,0.3301481604576111,-0.05198536440730095],[3,0.6842118517880439,0.003399336718629371,-0.0326651223778095,0.7285434620959083],[1,86.46655764127053,2.8486995752535376,-2.4612777391930423]],[12,"mixamorig_RightToeBase",53,[[11,"mixamorig_LeftToe_End_2",-65,[1,"77otOZgTlWCasBF1QZsBay",null,null,null,1,0],[1,-0.002630365313962102,0.03892634063959122,-3.999627452150323e-12]]],[1,"2fTmZs+GBcq7CdN/xd0WrP",null,null,null,1,0],[1,-0.011652672663331032,0.11107330024242401,-3.429912798225132e-9],[3,0.301251111647604,0.051754835689453986,0.009423684273514478,0.9520926419674473],[1,34.98449834321575,5.335371585072871,2.8158942937130167]],[41,"sol_苏尔",1,[[50,1,-66,[8,"13Qf0bJqFWoaygghgquMcT"],[0,1],[47,true,true],1,2,3]],[1,"e3kjFGC2BUzLfOt6yq9TkP",null,null,null,1,0]]],0,[0,0,1,0,2,1,0,-1,6,0,-2,55,0,-1,14,0,-2,17,0,-3,20,0,-4,23,0,-5,26,0,-1,32,0,-2,35,0,-3,38,0,-4,41,0,-5,44,0,-1,7,0,-2,47,0,-3,51,0,-1,9,0,-2,11,0,-3,29,0,-1,8,0,-1,10,0,4,10,0,-1,12,0,-1,13,0,-1,15,0,-1,16,0,4,16,0,-1,18,0,-1,19,0,4,19,0,-1,21,0,-1,22,0,4,22,0,-1,24,0,-1,25,0,4,25,0,-1,27,0,-1,28,0,4,28,0,-1,30,0,-1,31,0,-1,33,0,-1,34,0,4,34,0,-1,36,0,-1,37,0,4,37,0,-1,39,0,-1,40,0,4,40,0,-1,42,0,-1,43,0,4,43,0,-1,45,0,-1,46,0,4,46,0,-1,48,0,-1,49,0,-1,50,0,4,50,0,-1,52,0,-1,53,0,-1,54,0,4,54,0,2,55,0,9,1,2,4,13,3,4,31,4,4,6,5,4,8,66],[0,0,0,0],[-1,-2,5,13],[70,71,72,73]],[[[51,".bin",563777659,[{"primitives":[{"primitiveMode":7,"jointMapIndex":0,"vertexBundelIndices":[0],"indexView":{"offset":480168,"length":45426,"count":22713,"stride":2}},{"primitiveMode":7,"jointMapIndex":0,"vertexBundelIndices":[1],"indexView":{"offset":654978,"length":14190,"count":7095,"stride":2}}],"vertexBundles":[{"view":{"offset":0,"length":480168,"count":6669,"stride":72},"attributes":[{"name":"a_position","format":32,"isNormalized":false},{"name":"a_normal","format":32,"isNormalized":false},{"name":"a_texCoord","format":21,"isNormalized":false},{"name":"a_tangent","format":44,"isNormalized":false},{"name":"a_joints","format":42,"isNormalized":false},{"name":"a_weights","format":44,"isNormalized":false}]},{"view":{"offset":525594,"length":129384,"count":1797,"stride":72},"attributes":[{"name":"a_position","format":32,"isNormalized":false},{"name":"a_normal","format":32,"isNormalized":false},{"name":"a_texCoord","format":21,"isNormalized":false},{"name":"a_tangent","format":44,"isNormalized":false},{"name":"a_joints","format":42,"isNormalized":false},{"name":"a_weights","format":44,"isNormalized":false}]}],"jointMaps":[[0,1,2,3,4,5,7,8,9,10,11,12,13,15,16,17,19,20,21,23,24,25,27,28,29,31,32,33,34,35,36,37,39,40,41,43,44,45,47,48,49,51,52,53,55,56,57,58,60,61,62,63],[0,4,5,7,31]]},"minPosition",8,[1,-0.5594356060028076,0.003446301445364952,-0.6224960684776306],"maxPosition",8,[1,0.556531548500061,1.8539626598358154,0.2725532650947571]]],-1],0,0,[],[],[]],[[[17,"Material__107",[{"rasterizerState":{},"blendState":{"targets":[{}]},"depthStencilState":{}}],[{"USE_ALBEDO_MAP":true,"DCC_APP_NAME":0}],[[[{"albedoScale":1,"specularFactor":1,"shininessExponent":32,"emissiveScale":1},"mainColor",8,[4,4294967295],"specularColor",8,[4,4286348412],"emissive",8,[4,4278190080],"mainTexture",6,0]],11]]],0,0,[0,0],[6,7],[74,10]],[[[19,"003"],[22,"003",[-3,-4],[23,"4cSv7o5ahMHrusMuvKQ+VM",null,null,-2,0,[-1]],[1,7.162,0,0]],[28,0,{},[4,"9e+0VPM3RQdYTQijsQ4c4Z",null,null,-8,[32,"68AAqHWVJKOJnHomUbSC0Q",1,[[37,[2,["9e+0VPM3RQdYTQijsQ4c4Z"]],[[38,-7,[8,"5bUtNPrctMspeZEcY/x1As"],1]]]],[[34,"Bear",["_name"],[2,["9e+0VPM3RQdYTQijsQ4c4Z"]]],[10,["_lpos"],[2,["9e+0VPM3RQdYTQijsQ4c4Z"]],[1,0,0,0]],[10,["_lrot"],[2,["9e+0VPM3RQdYTQijsQ4c4Z"]],[3,0,0,0,1]],[10,["_euler"],[2,["9e+0VPM3RQdYTQijsQ4c4Z"]],[1,0,0,0]],[10,["_lscale"],[2,["9e+0VPM3RQdYTQijsQ4c4Z"]],[1,3,3,3]],[9,["_materials","0"],[2,["5dNs6MV+lRwLHRf/IfzHC3"]],2],[35,["_skinningRoot"],[2,["5dNs6MV+lRwLHRf/IfzHC3"]],-5],[9,["_materials","0"],[2,["b8BP1mCv1dxIF51lczs6+z"]],3],[35,["_skinningRoot"],[2,["b8BP1mCv1dxIF51lczs6+z"]],-6]],[[2,["a56m7eKjBdJbyqTMyCgE1i"]]]],0]],[29,"Main",1,[2],[1,"83H2ld40dEmZwKhUQs6mOv",null,null,null,1,0],[1,1.5,1.5,1.5]],[16,"Shadow",1,[[14,"Quad<ModelComponent>",-9,[8,"00++FWnMlHiaMXH1Vnl3Uj"],[4],[15],5]],[1,"2ebKwpC7dHgKxyx+xvb+a7",null,null,null,1,0],[3,-0.7071067811865475,0,0,0.7071067811865477],[1,3,3,1],[1,-89.99999999999999,0,0]]],0,[0,-1,2,0,0,1,0,-1,3,0,-2,4,0,3,2,0,3,2,0,2,2,0,0,2,0,2,4,0,9,1,2,4,3,9],[0,0,0,0,0,0],[1,12,3,3,-1,5],[75,76,77,78,1,0]]]]
